ram.v
//存储器文件ram.v
`timescale 1ns/10ps
module ram(
input               clock,
input[8:0]          addr,
input               wr,
input[31:0]         wdata,
input               rd,
output reg[31:0]    rdata
);

reg[31:0]           ram[127:0];   //RAM
always @(negedge clock) begin
    if (wr)begin
        ram[addr] <= wdata;       //向RAM中写入数据
    end
    if (rd) begin
        rdata <= ram[addr];       //从RAM中读取数据
    end
    else begin
        rdata <= 32'bz;           //读写均无效时，为高阻态。
    end
end
endmodule

//-----Testbench of ram-------//
module ram_tb;
reg             clock;
reg[8:0]        addr;
reg             wr, rd;
reg[31:0]       wdata;
wire[31:0]      rdata;

reg[63:0]       data_buffer;
reg[15:0]       addr_buffer;
ram ram(
                clock,
                addr,
                wr,
                wdata,
                rd,
                rdata
);
initial begin
    clock <= 0; rd <= 0; wr <= 0; wdata <= 0; addr <= 0;
    data_buffer[63:32] = {4'h2, 4'h2, 4'h4, 4'h5, 8'h0, 8'h0}; 
    data_buffer[31:0]  = {4'h1, 4'h0, 4'hf, 4'h0, 4'h0, 4'h0, 4'h1, 4'h0};
    addr_buffer[15:0]  = {8'h0, 8'h1};
    #10   addr <= addr_buffer[15:8]; wr <= 1; wdata <= data_buffer[63:32];
    #400  wr <= 0;
    #500  addr <= addr_buffer[7:0];  wr <= 1; wdata <= data_buffer[31:0];
    #900  addr <= addr_buffer[15:8]; wr <= 0; wdata <= 0; 
    #1000 rd <= 1;
    #1200 rd <= 0; addr <= addr_buffer[7:0];
    #1500 rd <= 1;
    #1900 rd <= 0;
    #2000 $stop;
end
always #5 clock <= ~clock;
initial begin
    $dumpfile("tb/ram_tb.vcd");
    $dumpvars(addr, wr, rd, wdata, rdata, addr);
end
endmodule

tb/Pics/Task1/ram_tb.vcd
$date
	Sat May 28 21:34:57 2022
$end
$version
	Icarus Verilog
$end
$timescale
	10ps
$end
$scope module ram_tb $end
$var wire 32 ! rdata [31:0] $end
$var reg 9 " addr [8:0] $end
$var reg 16 # addr_buffer [15:0] $end
$var reg 1 $ clock $end
$var reg 64 % data_buffer [63:0] $end
$var reg 1 & rd $end
$var reg 32 ' wdata [31:0] $end
$var reg 1 ( wr $end
$scope module ram $end
$var wire 9 ) addr [8:0] $end
$var wire 1 $ clock $end
$var wire 1 & rd $end
$var wire 32 * wdata [31:0] $end
$var wire 1 ( wr $end
$var reg 32 + rdata [31:0] $end
$upscope $end
$upscope $end
$enddefinitions $end
#0
$dumpvars
bz +
b100010010001010000000000000000 *
b0 )
1(
b100010010001010000000000000000 '
0&
b10001001000101000000000000000000010000111100000000000000010000 %
0$
b1 #
b0 "
bz !
$end
#1000
1$
#2000
b10000111100000000000000010000 '
b10000111100000000000000010000 *
b1 "
b1 )
0$
#3000
1$
#4000
1&
b0 '
b0 *
0(
b0 "
b0 )
0$
#5000
b100010010001010000000000000000 !
b100010010001010000000000000000 +
1$
#6000
b1 "
b1 )
0$
#7000
b10000111100000000000000010000 !
b10000111100000000000000010000 +
1$
#8000
b0 "
b0 )
0&
0$
#9000
bz !
bz +
1$
