alu.v
//算数逻辑运算单元 alu.v
module alu(
input[31:0]         aluA,
input[31:0]         aluB,
input[3:0]          alufun,
output[31:0]        valE,
output[2:0]         cc
);

wire                ZF, SF, OF;

wire signed[31:0]   A, B, E;
assign              A = aluA;
assign              B = aluB;
assign              E = valE;
assign              cc = {ZF, SF, OF};
assign valE = (alufun == 0) ? (aluA + aluB) : 
              (alufun == 1) ? (aluA - aluB) :
              //(alufun == 2) ? (aluA && aluB):
              //(alufun == 3) ? ((!aluA)&&aluB)||(aluA&&(!aluB)) :
              (alufun == 2) ? (aluA & aluB):
              (alufun == 3) ? ((~aluA)&aluB)|(aluA&(~aluB)) :
              32'bz;

//cc[2] = ZF, cc[1] = SF, cc[0] = OF.
assign ZF = (valE == 0) ? 1'b1 : 1'b0;
assign SF = (valE[31] == 1) ? 1'b1 : 1'b0;
assign OF = (alufun == 1) ? 
            ((((A > 0)&&(B < 0)&&(E <= 0))||((A < 0)&&(B > 0)&&(E >= 0))) ? 1 : 0) : 
             (((A < 0)&&(B < 0)&&(E >= 0))||((A >= 0)&&(B >= 0)&&(E < 0))) ? 1 : 0;

endmodule
/*
//-------Testbench of ALU-------//
module alu_tb;
reg[31:0]       aluA;
reg[31:0]       aluB;
reg[3:0]        alufun;
wire[31:0]      valE;
wire[2:0]       cc;
alu alu(
                aluA,
                aluB,
                alufun,
                valE,
                cc
);
//initial begin
//        alufun <= 0; aluA <= 32'h0AE20D6A; aluB <= 32'h59BB45EB; 
//    #30 alufun <= 1;
//    #30 alufun <= 2;
//    #30 alufun <= 3;
//    #80 $stop;
//end
initial begin
        alufun <= 2; aluA <= 32'h1100; aluB <= 32'h11;
    #20 alufun <= 1; aluA <= 32'h11; aluB <= 32'h133;
    #20 alufun <= 0; aluA <= 32'h7FFED28A; aluB <= 32'h7FFED28A;
    #20 alufun <= 1; aluA <= 32'hEECE2ADD; aluB <= 32'h7EFFC55C;
    #80 $stop;
end
initial begin
    $dumpfile("alu_tb_cc.vcd");
    $dumpvars();
end
endmodule
*/

regfile.v
//寄存器读写文件 regfile.v
`timescale 1ns/10ps
module regfile(
input[3:0]          dstE,
input[31:0]         valE,
input[3:0]          dstM,
input[31:0]         valM,
input[3:0]          rA,
input[3:0]          rB,
input               reset,
input               clock,
output[31:0]        valA,
output[31:0]        valB,
output[31:0]        r0,
output[31:0]        r1,
output[31:0]        r2,
output[31:0]        r3,
output[31:0]        r4,
output[31:0]        r5,
output[31:0]        r6,
output[31:0]        r7
);
reg[31:0]           r_r0, r_r1, r_r2, r_r3, r_r4, r_r5,r_r6, r_r7;
assign              valA = (rA == 0) ? r0 :
                           (rA == 1) ? r1 :
                           (rA == 2) ? r2 :
                           (rA == 3) ? r3 :
                           (rA == 4) ? r4 :
                           (rA == 5) ? r5 :
                           (rA == 6) ? r6 :
                           (rA == 7) ? r7 : 32'bz;
assign              valB = (rB == 0) ? r0 :
                           (rB == 1) ? r1 :
                           (rB == 2) ? r2 :
                           (rB == 3) ? r3 :
                           (rB == 4) ? r4 :
                           (rB == 5) ? r5 :
                           (rB == 6) ? r6 :
                           (rB == 7) ? r7 : 32'bz;
assign              r0   = r_r0;
assign              r1   = r_r1;
assign              r2   = r_r2;
assign              r3   = r_r3;
assign              r4   = r_r4;
assign              r5   = r_r5;
assign              r6   = r_r6;
assign              r7   = r_r7;
always @(posedge clock or negedge reset) begin
    if (reset)begin
        //r_valA <= 0; r_valB <= 0;
        r_r0 <= 0; r_r1 <= 0; r_r2 <= 0; r_r3 <= 0; 
        r_r4 <= 0; r_r5 <= 0; r_r6 <= 0; r_r7 <= 0; 
    end
    else begin
        case(dstE)
            0: begin r_r0 <= valE; end
            1: begin r_r1 <= valE; end
            2: begin r_r2 <= valE; end
            3: begin r_r3 <= valE; end
            4: begin r_r4 <= valE; end
            5: begin r_r5 <= valE; end
            6: begin r_r6 <= valE; end
            7: begin r_r7 <= valE; end
        endcase
        case(dstM)
            0: begin r_r0 <= valM; end
            1: begin r_r1 <= valM; end
            2: begin r_r2 <= valM; end
            3: begin r_r3 <= valM; end
            4: begin r_r4 <= valM; end
            5: begin r_r5 <= valM; end
            6: begin r_r6 <= valM; end
            7: begin r_r7 <= valM; end
        endcase
    end
end
endmodule

/*
module regfile_tb;
reg[3:0]          dstE;
reg[3:0]          dstM;
wire[31:0]        valE;
wire[31:0]        valM;
reg[3:0]          rA;
reg[3:0]          rB;
reg               reset;
reg               clock;
wire[31:0]        r0;
wire[31:0]        r1;
wire[31:0]        r2;
wire[31:0]        r3;
wire[31:0]        r4;
wire[31:0]        r5;
wire[31:0]        r6;
wire[31:0]        r7;

reg[31:0]         write_bufferE;
reg[31:0]         write_bufferM;
reg[12:0]         con;
assign            valE = write_bufferE;
assign            valM = write_bufferM;
regfile regfile(
                  dstE,
                  valE,
                  dstM,
                  valM,
                  rA,
                  rB,
                  reset,
                  clock,
                  valA,
                  valB,
                  r0, r1, r2, r3, r4, r5, r6, r7
);
initial begin
            clock <= 0; reset <= 1;
            dstE <= 0;  dstM <= 1; con <= 1;
            write_bufferE <= 32'hABCDEF98;
            write_bufferM <= 32'h7654321A;
    #37     reset <= 0;
    #2000   $stop;
end
always #10 clock = ~clock;
always @(posedge clock) begin
    if (con == 4-1)begin
        con <= 0;
    end
    else begin
        con <= con+1;
    end
    if (con == 0)begin
        write_bufferE[31:1] <= write_bufferE[30:0];
        write_bufferE[0]    <= write_bufferE[31];
        write_bufferM[31:1] <= write_bufferM[30:0];
        write_bufferM[0]    <= write_bufferM[31];
        dstE <= dstE + 2; dstM <= dstM + 2;
        if (dstE == 6)begin
            dstE <= 0;
        end
        if (dstM == 7)begin
            dstM <= 1;
        end
    end
end
initial begin
    $dumpfile("regfile_tb.vcd");
    $dumpvars;
end
endmodule */

ram.v
//存储器文件ram.v
`timescale 1ns/10ps
module ram(
input               clock,
input[8:0]          addr,
input               wr,
input[31:0]         wdata,
input               rd,
output reg[31:0]    rdata
);

reg[31:0]           ram[127:0];   //RAM
always @(negedge clock) begin
    if (wr)begin
        ram[addr] <= wdata;       //向RAM中写入数据
    end
    if (rd) begin
        rdata <= ram[addr];       //从RAM中读取数据
    end
    else begin
        rdata <= 32'bz;           //读写均无效时，为高阻态。
    end
end
endmodule

//-----Testbench of ram-------//
module ram_tb;
reg             clock;
reg[8:0]        addr;
reg             wr, rd;
reg[31:0]       wdata;
wire[31:0]      rdata;

reg[63:0]       data_buffer;
reg[15:0]       addr_buffer;
ram ram(
                clock,
                addr,
                wr,
                wdata,
                rd,
                rdata
);
initial begin
    clock <= 0; rd <= 0; wr <= 0; wdata <= 0; addr <= 0;
    data_buffer[63:32] = {4'h2, 4'h2, 4'h4, 4'h5, 8'h0, 8'h0}; 
    data_buffer[31:0]  = {4'h1, 4'h0, 4'hf, 4'h0, 4'h0, 4'h0, 4'h1, 4'h0};
    addr_buffer[15:0]  = {8'h0, 8'h1};
    #10   addr <= addr_buffer[15:8]; wr <= 1; wdata <= data_buffer[63:32];
    #400  wr <= 0;
    #500  addr <= addr_buffer[7:0];  wr <= 1; wdata <= data_buffer[31:0];
    #900  addr <= addr_buffer[15:8]; wr <= 0; wdata <= 0; 
    #1000 rd <= 1;
    #1200 rd <= 0; addr <= addr_buffer[7:0];
    #1500 rd <= 1;
    #1900 rd <= 0;
    #2000 $stop;
end
always #5 clock <= ~clock;
initial begin
    $dumpfile("tb/ram_tb.vcd");
    $dumpvars(addr, wr, rd, wdata, rdata, addr);
end
endmodule

processor.v
//处理器Z的顶层文件 processor.v
`timescale 1ns/10ps
module processor(
input           clock,
input[8:0]      addr,
input           wr,
input[31:0]     wdata,
input           working,
input[3:0]      rID,
//output[31:0]    valA,
//output[31:0]    valB,
output[31:0]    valE,
output[31:0]    r0,
output[31:0]    r1,
output[31:0]    r2,
output[31:0]    r3,
output[31:0]    r4,
output[31:0]    r5,
output[31:0]    r6,
output[31:0]    r7,
output[31:0]    rdata
//output[3:0]     icode,
//output[3:0]     ifun,
//output[3:0]     rA,
//output[3:0]     rB,
//output[15:0]    valC
);
parameter IRMOV = 8'h10;
parameter ADD   = 8'h20;
parameter SUB   = 8'h21;
parameter AND   = 8'h22;
parameter XOR   = 8'h23;
ram ram(
                .clock(clock),
                .addr(f_addr),
                .wr(wr),
                .wdata(wdata),
                .rd(f_rd),
                .rdata(f_rdata)
);
regfile regfile(
                .dstE(w_dstE),
                .valE(w_valE),
                .dstM(w_dstM),
                .valM(w_valM),
                .rA(d_rA),
                .rB(d_rB),
                .reset(e_reg_rst),
                .clock(clock),
                .valA(d_valA),
                .valB(d_valB),
                .r0(r0),
                .r1(r1),
                .r2(r2),
                .r3(r3),
                .r4(r4),
                .r5(r5),
                .r6(r6),
                .r7(r7)
);
alu alu(
                .aluA(e_valA),
                .aluB(e_valB),
                .alufun(e_alufun),
                .valE(e_valE)
);
//-----Fetch stage signals-----//
reg[8:0]        PC = 0;
wire[8:0]       f_addr;
wire            f_rd;
wire[31:0]      f_rdata;
wire[31:0]      F_read;
//------------Fetch--------------//
assign f_addr = (working) ? PC   : addr;
assign f_rd     = (working) ? 1    : 0;
assign F_read = f_rdata;
always @(posedge clock) begin
    if (working)begin
        PC <= PC + 1;
    end
end

//------Decode stage signals-----//
reg[3:0]        d_icode = 4'bz;
reg[3:0]        d_ifun  = 4'bz;
reg[3:0]        d_rA    = 4'bz;
reg[3:0]        d_rB    = 4'bz;
reg[15:0]       d_valC  = 16'bz;
wire[31:0]      d_valA  = 32'bz;
wire[31:0]      d_valB  = 32'bz;
reg[3:0]        D_icode = 4'bz;
reg[3:0]        D_ifun  = 4'bz;
reg[3:0]        D_rA    = 4'bz;
reg[3:0]        D_rB    = 4'bz;
reg[31:0]       D_valA  = 32'bz;
reg[31:0]       D_valB  = 32'bz;
reg[15:0]       D_valC  = 16'bz;
//-------------Decode------------//
//assign icode  = D_icode;
//assign ifun   = D_ifun;
//assign rA     = D_rB;
//assign rB     = D_rB;
//assign valC   = D_valC;
//assign valA     = d_valA;
//assign valB     = d_valB;
//assign d_rA     = D_rA;
//assign d_rB     = D_rB;         
always @(posedge clock) begin
    if (working)begin
        d_icode <= F_read[31:28];
        d_ifun  <= F_read[27:24];
        d_rA    <= F_read[23:20];
        d_rB    <= F_read[19:16];
        d_valC  <= F_read[15: 0];
        D_icode <= d_icode;
        D_ifun  <= d_ifun;
        D_rA    <= d_rA;
        D_rB    <= d_rB;
        D_valC  <= d_valC;
        D_valA  <= d_valA;
        D_valB  <= d_valB;
    end
end

//------Execute stage signals-----//
reg[3:0]          E_dstM = 4'bz;
reg[31:0]         E_valM = 32'bz;
reg               e_reg_rst;
wire[31:0]        e_valA = 32'bz;
wire[31:0]        e_valB = 32'bz;
wire[3:0]         e_alufun = 4'bz;
wire[31:0]        e_valE = 32'bz;
reg[3:0]          E_dstE = 4'bz;
reg[31:0]         E_valE = 32'bz;
initial begin
        e_reg_rst <= 1;
    #20 e_reg_rst <= 0;
end
//----------Execute stage---------//
assign            valE   = e_valE; 
assign            e_valA = D_valA;
assign            e_valB = D_valB;
assign            e_alufun = 
                  ({D_icode, D_ifun} == ADD) ? 0 :
                  ({D_icode, D_ifun} == SUB) ? 1 :
                  ({D_icode, D_ifun} == AND) ? 2 :
                  ({D_icode, D_ifun} == XOR) ? 3 : 4'bz;
always @(posedge clock) begin
    if ({D_icode, D_ifun} == IRMOV)begin
        E_dstM <= D_rB;
        E_valM <= D_valC;
    end
    else begin
        E_dstM <= 4'bz;
        E_valM <= 32'bz;
    end
    E_dstE <= D_rA;
    E_valE <= e_valE;
end

//----Write-back stage signals----//
reg[3:0]          w_dstM = 4'bz;
reg[31:0]         w_valM = 32'bz;
reg[3:0]          w_dstE = 4'bz;
reg[31:0]         w_valE = 32'bz;
assign            rdata  = (rID == 0) ? r0 :
                           (rID == 1) ? r1 :
                           (rID == 2) ? r2 :
                           (rID == 3) ? r3 :
                           (rID == 4) ? r4 :
                           (rID == 5) ? r5 :
                           (rID == 6) ? r6 :
                           (rID == 7) ? r7 : 32'bz;
//-----------Write-back-----------//
always @(posedge clock) begin
        w_dstM <= E_dstM;
        w_valM <= E_valM;
        w_dstE <= E_dstE;
        w_valE <= E_valE;
end
endmodule

//-----Testbench of processor(Task 5)-----//
module pro_tb4;
reg             clock;
reg[8:0]        addr;
reg             wr;
reg[31:0]       wdata;
reg             working;
reg[3:0]        rID;
//wire[31:0]      valA, valB; 
wire[31:0]      valE;
wire[31:0]      r0, r1, r2, r3, r4, r5, r6, r7;
wire[31:0]      rdata;
reg             flg = 0;
//wire[3:0]       icode;
//wire[3:0]       ifun;
//wire[3:0]       rA;
//wire[3:0]       rB;
//wire[15:0]      valC;
//wire[31:0]      valE;
processor processor(
                clock,
                addr,
                wr,
                wdata,
                working,
                rID,
                //icode,
                //ifun,
                //rA,
                //rB,
                //valC,
                //valA,
                //valB,
                valE,
                r0, r1, r2, r3, r4, r5, r6, r7,
                rdata
                //valE
);
initial begin
    clock <= 0; addr <= 0; wr <= 0; wdata <= 0; working <= 0; rID <= 4'b1111;
    #20         addr <= 0; wr <= 1; wdata <= 32'h10F00080;
    #20         addr <= 1; wr <= 1; wdata <= 32'h10F10081;
    #20         addr <= 2; wr <= 1; wdata <= 32'h10F20082;
    #20         addr <= 3; wr <= 1; wdata <= 32'h10F30083;
    #20         addr <= 4; wr <= 1; wdata <= 32'h10F40084;
    #20         addr <= 5; wr <= 1; wdata <= 32'h10F50085;
    #20         addr <= 6; wr <= 1; wdata <= 32'h10F60086;
    #20         addr <= 7; wr <= 1; wdata <= 32'h10F70087;
    #20         addr <= 8; wr <= 1; wdata <= 32'h20010000;
    #20         addr <= 9; wr <= 1; wdata <= 32'h21230000;
    #20         addr <= 10;wr <= 1; wdata <= 32'h22450000;
    #20         addr <= 11;wr <= 1; wdata <= 32'h23670000;
    //Task 5 added
    #20         addr <= 12;wr <= 1; wdata <= 32'h21540000;
    #20         addr <= 13;wr <= 1; wdata <= 32'h22760000;
    #20         addr <= 14;wr <= 1; wdata <= 32'h20320000;
    #20         addr <= 15;wr <= 1; wdata <= 32'h23100000;
    #20         addr <= 16;wr <= 1; wdata <= 32'h20350000;
    #20         addr <= 17;wr <= 1; wdata <= 32'h21240000;
    #20         addr <= 18;wr <= 1; wdata <= 32'h23060000;
    #20         addr <= 19;wr <= 1; wdata <= 32'h22170000;
    #20         addr <= 0; wr <= 0; wdata <= 0;
    #10         working <= 1;
    #560        working <= 0; flg <= 1;
    #1000       $stop;
end
always #10 clock = ~clock;
always @(posedge clock ) begin
    if (flg)begin
        rID <= rID + 1;
    end
end
initial begin
    $dumpfile("pro_tb5.vcd");
    $dumpvars();
end
endmodule

/*
//-----Testbench of processor-----//
module pro_tb4;
reg             clock;
reg[8:0]        addr;
reg             wr;
reg[31:0]       wdata;
reg             working;
//reg[3:0]        rID;
//wire[31:0]      valA, valB; 
wire[31:0]      valE;
wire[31:0]      r0, r1, r2, r3, r4, r5, r6, r7;
//wire[31:0]      rdata;
//wire[3:0]       icode;
//wire[3:0]       ifun;
//wire[3:0]       rA;
//wire[3:0]       rB;
//wire[15:0]      valC;
//wire[31:0]      valE;
processor processor(
                clock,
                addr,
                wr,
                wdata,
                working,
                //rID,
                //icode,
                //ifun,
                //rA,
                //rB,
                //valC,
                //valA,
                //valB,
                valE,
                r0, r1, r2, r3, r4, r5, r6, r7
                //rdata
                //valE
);
initial begin
    clock <= 0; addr <= 0; wr <= 0; wdata <= 0; working <= 0; //rID <=0;
    #20         addr <= 0; wr <= 1; wdata <= 32'h10F00080;
    #20         addr <= 1; wr <= 1; wdata <= 32'h10F10081;
    #20         addr <= 2; wr <= 1; wdata <= 32'h10F20082;
    #20         addr <= 3; wr <= 1; wdata <= 32'h10F30083;
    #20         addr <= 4; wr <= 1; wdata <= 32'h10F40084;
    #20         addr <= 5; wr <= 1; wdata <= 32'h10F50085;
    #20         addr <= 6; wr <= 1; wdata <= 32'h10F60086;
    #20         addr <= 7; wr <= 1; wdata <= 32'h10F70087;
    #20         addr <= 8; wr <= 1; wdata <= 32'h20010000;
    #20         addr <= 9; wr <= 1; wdata <= 32'h21230000;
    #20         addr <= 10;wr <= 1; wdata <= 32'h22450000;
    #20         addr <= 11;wr <= 1; wdata <= 32'h23670000;
    #20         addr <= 0; wr <= 0; wdata <= 0;
    #10         working <= 1;
    #500        $stop;
end
always #10 clock = ~clock;
initial begin
    $dumpfile("pro_tb4.vcd");
    $dumpvars();
end
endmodule
*/

/*
//-----Testbench of processor (Task 1)-------//
module pro_tb;
reg             clock;
reg[8:0]        addr;
reg             wr;
reg[31:0]       wdata;
reg             working;
wire[3:0]       icode;
wire[3:0]       ifun;
wire[3:0]       rA;
wire[3:0]       rB;
wire[15:0]      valC; 
processor processor(
                clock,
                addr,
                wr,
                wdata,
                working,
                icode,
                ifun,
                rA,
                rB,
                valC
);
initial begin
    clock <= 0; addr <= 0; wdata <= 32'h00000000; wr <= 0; working <= 0;
    #20         addr <= 0; wdata <= 32'h10f00010; wr <= 1;
    #20         addr <= 1; wdata <= 32'h20010000;
    #20         addr <= 2; wdata <= 32'h21230000;
    #20         addr <= 3; wdata <= 32'h22450000;
    #20         addr <= 4; wdata <= 32'h23670000;
    #20         addr <= 0; wdata <= 32'h00000000; wr <= 0; working <= 1;
    //#20         working <= 1;
    #150        $stop;
end
always #10 clock = ~clock;
initial begin
    $dumpfile("pro_tb.vcd");
    $dumpvars;
end
endmodule*/

/*module processor(
input           clock,
input[8:0]      addr,
input           wr,
input[31:0]     wdata,
input           working,
output[3:0]     icode,
output[3:0]     ifun,
output[3:0]     rA,
output[3:0]     rB,
output[15:0]    valC,
//output[15:0]    valD, /////////
output[31:0]    r0,
output[31:0]    r1,
output[31:0]    r2,
output[31:0]    r3,
output[31:0]    r4,
output[31:0]    r5,
output[31:0]    r6,
output[31:0]    r7,
output[31:0]    valA,
output[31:0]    valB,
output[31:0]    valE
);

//wire            read = 0;
//reg[8:0]       addr_buffer;
//reg[31:0]      read_buffer = 0;
//assign icode = read_buffer[31:28];
//assign ifun  = read_buffer[27:24];
//assign rA    = read_buffer[23:20];
//assign rB    = read_buffer[19:16];
//assign valC  = read_buffer[15: 0];

wire[8:0]       addr_w;
wire[31:0]      read_w;
reg[8:0]        PC = 0;
reg             read = 0; //3
reg[3:0]        dstE_reg = 4'hF;
reg[3:0]        dstM = 0;
reg[31:0]       valM = 0;
reg[15:0]       valC;
reg             reg_rst;
wire[31:0]      aluA;
wire[31:0]      aluB;
reg[3:0]        alufun;
wire[31:0]      aluValE;
// Separate instruction fetching and decoding
// adding a pipeline
reg[3:0]        icode;
reg[3:0]        ifun;
reg[3:0]        rA;
reg[3:0]        rB;
//assign icode  = read_w[31:28];
//assign ifun   = read_w[27:24];
//assign rA     = read_w[23:20];
//assign rB     = read_w[19:16];
//
assign addr_w = (working) ? PC : addr;
assign aluA   = valA;
assign aluB   = valB;
assign valE   = aluValE;
//assign valE_reg = valE;
//assign valC   = read_w[15: 0];
//assign read   = (working) ? 1  : 0;

ram ram(
                .clock(clock),
                .addr(addr_w),
                .wr(wr),
                .wdata(wdata),
                .rd(read),
                .rdata(read_w)
);
regfile regfile(
                .dstE(dstE_reg),
                .valE(aluValE),
                .dstM(dstM),
                .valM(valM),
                .rA(rA),
                .rB(rB),
                .reset(reg_rst),
                .clock(clock),
                .r0(r0),
                .r1(r1),
                .r2(r2),
                .r3(r3),
                .r4(r4),
                .r5(r5),
                .r6(r6),
                .r7(r7),
                .valA(valA),
                .valB(valB)
);
alu alu(
        .aluA(aluA),
        .aluB(aluB),
        .alufun(alufun),
        .valE(aluValE)
);

initial begin
        reg_rst <= 1;
    #20 reg_rst <= 0;
end

always @(posedge clock) begin
    if(working)begin
        //addr_w <= PC;
        //read_buffer <= read_w;
        read = 1; 
        PC <= PC+1;
        icode <= read_w[31:28];
        ifun  <= read_w[27:24];
        valC  <= read_w[15: 0];//////////
        rA    <= read_w[23:20];
        rB    <= read_w[19:16];
        case(read_w[31:24])
            8'h10: begin
                dstM <= read_w[19:16];
                valM <= read_w[15: 0]; 
            end            
            8'h20: begin
                alufun <= 0;
                dstE_reg <= rA;
                //valE_reg <= valE;
            end
            8'h21: begin
                alufun <= 1;
                dstE_reg <= rA;
                //valE_reg <= valE;
            end
            8'h22: begin
                alufun <= 2;
                dstE_reg <= rA;
               //valE_reg <= valE;
            end
            8'h23: begin
                alufun <= 3;
                dstE_reg <= rA;
               //valE_reg <= valE;
            end
        endcase
    end
    else begin
        if (wr)begin
        read = 0; //
        //addr_w <= addr;
        //read_buffer <= read_w;
        //icode <= read_buffer[31:28];
        end
    end
end
endmodule

module pro_tb2;
reg             clock;
reg[8:0]        addr;
reg             wr;
reg[31:0]       wdata;
reg             working;
wire[3:0]       icode;
wire[3:0]       ifun;
wire[3:0]       rA;
wire[3:0]       rB;
wire[15:0]      valC;
//wire[15:0]      valD;/////////
wire[31:0]      valB, valA; 
wire[31:0]      r0, r1, r2, r3, r4, r5, r6, r7;
wire[31:0]      valE;
processor processor(
                clock,
                addr,
                wr,
                wdata,
                working,
                icode,
                ifun,
                rA,
                rB,
                valC,
                r0, r1, r2, r3, r4, r5, r6, r7,
                valA,
                valB,
                valE
);
initial begin
    clock <= 0; addr <= 0; wr <= 0; wdata <= 0; working <= 0;
    #20         addr <= 0; wr <= 1; wdata <= 32'h10F00080;
    #20         addr <= 1; wr <= 1; wdata <= 32'h10F10081;
    #20         addr <= 2; wr <= 1; wdata <= 32'h10F20082;
    #20         addr <= 3; wr <= 1; wdata <= 32'h10F30083;
    #20         addr <= 4; wr <= 1; wdata <= 32'h10F40084;
    #20         addr <= 5; wr <= 1; wdata <= 32'h10F50085;
    #20         addr <= 6; wr <= 1; wdata <= 32'h10F60086;
    #20         addr <= 7; wr <= 1; wdata <= 32'h10F70087;
    #20         addr <= 8; wr <= 1; wdata <= 32'h20010000;
    #20         addr <= 9; wr <= 1; wdata <= 32'h21230000;
    #20         addr <= 10;wr <= 1; wdata <= 32'h22450000;
    #20         addr <= 11;wr <= 1; wdata <= 32'h23670000;
    #20         addr <= 0; wr <= 0; wdata <= 0;
    #10         working <= 1;
    #500        $stop;
end
always #10 clock = ~clock;
initial begin
    $dumpfile("tb/pro_tb4.vcd");
    $dumpvars();
end
endmodule
*/

tb/Simulations/pro_tb5.vcd
$date
	Wed Jun 01 02:40:20 2022
$end
$version
	Icarus Verilog
$end
$timescale
	10ps
$end
$scope module pro_tb4 $end
$var wire 32 ! valE [31:0] $end
$var wire 32 " rdata [31:0] $end
$var wire 32 # r7 [31:0] $end
$var wire 32 $ r6 [31:0] $end
$var wire 32 % r5 [31:0] $end
$var wire 32 & r4 [31:0] $end
$var wire 32 ' r3 [31:0] $end
$var wire 32 ( r2 [31:0] $end
$var wire 32 ) r1 [31:0] $end
$var wire 32 * r0 [31:0] $end
$var reg 9 + addr [8:0] $end
$var reg 1 , clock $end
$var reg 1 - flg $end
$var reg 4 . rID [3:0] $end
$var reg 32 / wdata [31:0] $end
$var reg 1 0 working $end
$var reg 1 1 wr $end
$scope module processor $end
$var wire 32 2 F_read [31:0] $end
$var wire 9 3 addr [8:0] $end
$var wire 1 , clock $end
$var wire 32 4 e_valA [31:0] $end
$var wire 32 5 e_valB [31:0] $end
$var wire 4 6 rID [3:0] $end
$var wire 32 7 valE [31:0] $end
$var wire 32 8 wdata [31:0] $end
$var wire 1 0 working $end
$var wire 1 1 wr $end
$var wire 32 9 rdata [31:0] $end
$var wire 32 : r7 [31:0] $end
$var wire 32 ; r6 [31:0] $end
$var wire 32 < r5 [31:0] $end
$var wire 32 = r4 [31:0] $end
$var wire 32 > r3 [31:0] $end
$var wire 32 ? r2 [31:0] $end
$var wire 32 @ r1 [31:0] $end
$var wire 32 A r0 [31:0] $end
$var wire 32 B f_rdata [31:0] $end
$var wire 1 C f_rd $end
$var wire 9 D f_addr [8:0] $end
$var wire 32 E e_valE [31:0] $end
$var wire 4 F e_alufun [3:0] $end
$var wire 32 G d_valB [31:0] $end
$var wire 32 H d_valA [31:0] $end
$var reg 4 I D_icode [3:0] $end
$var reg 4 J D_ifun [3:0] $end
$var reg 4 K D_rA [3:0] $end
$var reg 4 L D_rB [3:0] $end
$var reg 32 M D_valA [31:0] $end
$var reg 32 N D_valB [31:0] $end
$var reg 16 O D_valC [15:0] $end
$var reg 4 P E_dstE [3:0] $end
$var reg 4 Q E_dstM [3:0] $end
$var reg 32 R E_valE [31:0] $end
$var reg 32 S E_valM [31:0] $end
$var reg 9 T PC [8:0] $end
$var reg 4 U d_icode [3:0] $end
$var reg 4 V d_ifun [3:0] $end
$var reg 4 W d_rA [3:0] $end
$var reg 4 X d_rB [3:0] $end
$var reg 16 Y d_valC [15:0] $end
$var reg 1 Z e_reg_rst $end
$var reg 4 [ w_dstE [3:0] $end
$var reg 4 \ w_dstM [3:0] $end
$var reg 32 ] w_valE [31:0] $end
$var reg 32 ^ w_valM [31:0] $end
$scope module alu $end
$var wire 32 _ aluA [31:0] $end
$var wire 32 ` aluB [31:0] $end
$var wire 4 a alufun [3:0] $end
$var wire 32 b valE [31:0] $end
$upscope $end
$scope module ram $end
$var wire 9 c addr [8:0] $end
$var wire 1 , clock $end
$var wire 1 C rd $end
$var wire 32 d wdata [31:0] $end
$var wire 1 1 wr $end
$var reg 32 e rdata [31:0] $end
$upscope $end
$scope module regfile $end
$var wire 1 , clock $end
$var wire 4 f dstE [3:0] $end
$var wire 4 g dstM [3:0] $end
$var wire 4 h rA [3:0] $end
$var wire 4 i rB [3:0] $end
$var wire 1 Z reset $end
$var wire 32 j valE [31:0] $end
$var wire 32 k valM [31:0] $end
$var wire 32 l valB [31:0] $end
$var wire 32 m valA [31:0] $end
$var wire 32 n r7 [31:0] $end
$var wire 32 o r6 [31:0] $end
$var wire 32 p r5 [31:0] $end
$var wire 32 q r4 [31:0] $end
$var wire 32 r r3 [31:0] $end
$var wire 32 s r2 [31:0] $end
$var wire 32 t r1 [31:0] $end
$var wire 32 u r0 [31:0] $end
$var reg 32 v r_r0 [31:0] $end
$var reg 32 w r_r1 [31:0] $end
$var reg 32 x r_r2 [31:0] $end
$var reg 32 y r_r3 [31:0] $end
$var reg 32 z r_r4 [31:0] $end
$var reg 32 { r_r5 [31:0] $end
$var reg 32 | r_r6 [31:0] $end
$var reg 32 } r_r7 [31:0] $end
$upscope $end
$upscope $end
$upscope $end
$enddefinitions $end
#0
$dumpvars
bx }
bx |
bx {
bx z
bx y
bx x
bx w
bx v
bx u
bx t
bx s
bx r
bx q
bx p
bx o
bx n
bx m
bx l
bz k
bz j
bz i
bz h
bz g
bz f
bz e
b0 d
b0 c
bx b
bx a
bz `
bz _
bz ^
bz ]
bz \
bz [
1Z
bz Y
bz X
bz W
bz V
bz U
b0 T
bz S
bz R
bz Q
bz P
bz O
bz N
bz M
bz L
bz K
bz J
bz I
bx H
bx G
bx F
bx E
b0 D
0C
bz B
bx A
bx @
bx ?
bx >
bx =
bx <
bx ;
bx :
bz 9
b0 8
bx 7
b1111 6
bz 5
bz 4
b0 3
bz 2
01
00
b0 /
b1111 .
0-
0,
b0 +
bx *
bx )
bx (
bx '
bx &
bx %
bx $
bx #
bz "
bx !
$end
#1000
bx R
b0 #
b0 :
b0 n
b0 }
b0 $
b0 ;
b0 o
b0 |
b0 %
b0 <
b0 p
b0 {
b0 &
b0 =
b0 q
b0 z
b0 '
b0 >
b0 r
b0 y
b0 (
b0 ?
b0 s
b0 x
b0 )
b0 @
b0 t
b0 w
b0 *
b0 A
b0 u
b0 v
1,
#2000
b10000111100000000000010000000 /
b10000111100000000000010000000 8
b10000111100000000000010000000 d
11
0Z
0,
#3000
bx ]
bx j
1,
#4000
b1 D
b1 c
b10000111100010000000010000001 /
b10000111100010000000010000001 8
b10000111100010000000010000001 d
b1 +
b1 3
0,
#5000
1,
#6000
b10 D
b10 c
b10000111100100000000010000010 /
b10000111100100000000010000010 8
b10000111100100000000010000010 d
b10 +
b10 3
0,
#7000
1,
#8000
b11 D
b11 c
b10000111100110000000010000011 /
b10000111100110000000010000011 8
b10000111100110000000010000011 d
b11 +
b11 3
0,
#9000
1,
#10000
b100 D
b100 c
b10000111101000000000010000100 /
b10000111101000000000010000100 8
b10000111101000000000010000100 d
b100 +
b100 3
0,
#11000
1,
#12000
b101 D
b101 c
b10000111101010000000010000101 /
b10000111101010000000010000101 8
b10000111101010000000010000101 d
b101 +
b101 3
0,
#13000
1,
#14000
b110 D
b110 c
b10000111101100000000010000110 /
b10000111101100000000010000110 8
b10000111101100000000010000110 d
b110 +
b110 3
0,
#15000
1,
#16000
b111 D
b111 c
b10000111101110000000010000111 /
b10000111101110000000010000111 8
b10000111101110000000010000111 d
b111 +
b111 3
0,
#17000
1,
#18000
b1000 D
b1000 c
b100000000000010000000000000000 /
b100000000000010000000000000000 8
b100000000000010000000000000000 d
b1000 +
b1000 3
0,
#19000
1,
#20000
b1001 D
b1001 c
b100001001000110000000000000000 /
b100001001000110000000000000000 8
b100001001000110000000000000000 d
b1001 +
b1001 3
0,
#21000
1,
#22000
b1010 D
b1010 c
b100010010001010000000000000000 /
b100010010001010000000000000000 8
b100010010001010000000000000000 d
b1010 +
b1010 3
0,
#23000
1,
#24000
b1011 D
b1011 c
b100011011001110000000000000000 /
b100011011001110000000000000000 8
b100011011001110000000000000000 d
b1011 +
b1011 3
0,
#25000
1,
#26000
b1100 D
b1100 c
b100001010101000000000000000000 /
b100001010101000000000000000000 8
b100001010101000000000000000000 d
b1100 +
b1100 3
0,
#27000
1,
#28000
b1101 D
b1101 c
b100010011101100000000000000000 /
b100010011101100000000000000000 8
b100010011101100000000000000000 d
b1101 +
b1101 3
0,
#29000
1,
