regfile.v
//寄存器读写文件 regfile.v
`timescale 1ns/10ps
module regfile(
input[3:0]          dstE,
input[31:0]         valE,
input[3:0]          dstM,
input[31:0]         valM,
input               reset,
input               clock,
output[31:0]        r0,
output[31:0]        r1,
output[31:0]        r2,
output[31:0]        r3,
output[31:0]        r4,
output[31:0]        r5,
output[31:0]        r6,
output[31:0]        r7
);
reg[31:0]           r0, r1, r2, r3, r4, r5,r6, r7;

always @(posedge clock or negedge reset) begin
    if (reset)begin
        r0 <= 0; r1 <= 0; r2 <= 0; r3 <= 0; 
        r4 <= 0; r5 <= 0; r6 <= 0; r7 <= 0; 
    end
    else begin
        case(dstE)
            0: begin r0 <= valE; end
            1: begin r1 <= valE; end
            2: begin r2 <= valE; end
            3: begin r3 <= valE; end
            4: begin r4 <= valE; end
            5: begin r5 <= valE; end
            6: begin r6 <= valE; end
            7: begin r7 <= valE; end
        endcase
        case(dstM)
            0: begin r0 <= valM; end
            1: begin r1 <= valM; end
            2: begin r2 <= valM; end
            3: begin r3 <= valM; end
            4: begin r4 <= valM; end
            5: begin r5 <= valM; end
            6: begin r6 <= valM; end
            7: begin r7 <= valM; end
        endcase        
    end
end
endmodule

module regfile_tb;
reg[3:0]          dstE;
reg[3:0]          dstM;
wire[31:0]        valE;
wire[31:0]        valM;
reg               reset;
reg               clock;
wire[31:0]        r0;
wire[31:0]        r1;
wire[31:0]        r2;
wire[31:0]        r3;
wire[31:0]        r4;
wire[31:0]        r5;
wire[31:0]        r6;
wire[31:0]        r7;

reg[31:0]         write_bufferE;
reg[31:0]         write_bufferM;
reg[12:0]         con;
assign            valE = write_bufferE;
assign            valM = write_bufferM;
regfile regfile(
                  dstE,
                  valE,
                  dstM,
                  valM,
                  reset,
                  clock,
                  r0, r1, r2, r3, r4, r5, r6, r7
);
initial begin
            clock <= 0; reset <= 1;
            dstE <= 0;  dstM <= 1; con <= 1;
            write_bufferE <= 32'hABCDEF98;
            write_bufferM <= 32'h7654321A;
    #37     reset <= 0;
    #2000   $stop;
end
always #10 clock = ~clock;
always @(posedge clock) begin
    if (con == 4-1)begin
        con <= 0;
    end
    else begin
        con <= con+1;
    end
    if (con == 0)begin
        write_bufferE[31:1] <= write_bufferE[30:0];
        write_bufferE[0]    <= write_bufferE[31];
        write_bufferM[31:1] <= write_bufferM[30:0];
        write_bufferM[0]    <= write_bufferM[31];
        dstE <= dstE + 2; dstM <= dstM + 2;
        if (dstE == 6)begin
            dstE <= 0;
        end
        if (dstM == 7)begin
            dstM <= 1;
        end
    end
end
initial begin
    $dumpfile("regfile_tb.vcd");
    $dumpvars;
end
endmodule

tb/Pics/Task2/regfile_tb.vcd
$date
	Sun May 29 17:30:46 2022
$end
$version
	Icarus Verilog
$end
$timescale
	10ps
$end
$scope module regfile_tb $end
$var wire 32 ! valE [31:0] $end
$var wire 32 " valM [31:0] $end
$var wire 32 # r7 [31:0] $end
$var wire 32 $ r6 [31:0] $end
$var wire 32 % r5 [31:0] $end
$var wire 32 & r4 [31:0] $end
$var wire 32 ' r3 [31:0] $end
$var wire 32 ( r2 [31:0] $end
$var wire 32 ) r1 [31:0] $end
$var wire 32 * r0 [31:0] $end
$var reg 1 + clock $end
$var reg 13 , con [12:0] $end
$var reg 4 - dstE [3:0] $end
$var reg 4 . dstM [3:0] $end
$var reg 1 / reset $end
$var reg 32 0 write_bufferE [31:0] $end
$var reg 32 1 write_bufferM [31:0] $end
$scope module regfile $end
$var wire 1 + clock $end
$var wire 4 2 dstE [3:0] $end
$var wire 4 3 dstM [3:0] $end
$var wire 1 / reset $end
$var wire 32 4 valE [31:0] $end
$var wire 32 5 valM [31:0] $end
$var reg 32 6 r0 [31:0] $end
$var reg 32 7 r1 [31:0] $end
$var reg 32 8 r2 [31:0] $end
$var reg 32 9 r3 [31:0] $end
$var reg 32 : r4 [31:0] $end
$var reg 32 ; r5 [31:0] $end
$var reg 32 < r6 [31:0] $end
$var reg 32 = r7 [31:0] $end
$upscope $end
$upscope $end
$enddefinitions $end
#0
$dumpvars
bx =
bx <
bx ;
bx :
bx 9
bx 8
bx 7
bx 6
b1110110010101000011001000011010 5
b10101011110011011110111110011000 4
b1 3
b0 2
b1110110010101000011001000011010 1
b10101011110011011110111110011000 0
1/
b1 .
b0 -
b1 ,
0+
bx *
bx )
bx (
bx '
bx &
bx %
bx $
bx #
b1110110010101000011001000011010 "
b10101011110011011110111110011000 !
$end
#1000
b0 #
b0 =
b0 $
b0 <
b0 %
b0 ;
b0 &
b0 :
b0 '
b0 9
b0 (
b0 8
b0 )
b0 7
b0 *
b0 6
b10 ,
1+
#2000
0+
#3000
b11 ,
1+
#3700
b1110110010101000011001000011010 )
b1110110010101000011001000011010 7
b10101011110011011110111110011000 *
b10101011110011011110111110011000 6
0/
#4000
0+
#5000
b0 ,
1+
#6000
0+
#7000
b11 .
b11 3
b10 -
b10 2
b11101100101010000110010000110100 "
b11101100101010000110010000110100 5
b11101100101010000110010000110100 1
b1010111100110111101111100110001 !
b1010111100110111101111100110001 4
b1010111100110111101111100110001 0
b1 ,
1+
#8000
0+
#9000
b11101100101010000110010000110100 '
b11101100101010000110010000110100 9
b1010111100110111101111100110001 (
b1010111100110111101111100110001 8
b10 ,
1+
#10000
0+
#11000
b11 ,
1+
#12000
0+
#13000
b0 ,
1+
#14000
0+
#15000
b101 .
b101 3
b100 -
b100 2
b11011001010100001100100001101001 "
b11011001010100001100100001101001 5
b11011001010100001100100001101001 1
b10101111001101111011111001100010 !
b10101111001101111011111001100010 4
b10101111001101111011111001100010 0
b1 ,
1+
#16000
0+
#17000
b11011001010100001100100001101001 %
b11011001010100001100100001101001 ;
b10101111001101111011111001100010 &
b10101111001101111011111001100010 :
b10 ,
1+
#18000
0+
#19000
b11 ,
1+
#20000
0+
#21000
b0 ,
1+
#22000
0+
#23000
b111 .
b111 3
b110 -
b110 2
b10110010101000011001000011010011 "
b10110010101000011001000011010011 5
b10110010101000011001000011010011 1
b1011110011011110111110011000101 !
b1011110011011110111110011000101 4
b1011110011011110111110011000101 0
b1 ,
1+
#24000
0+
#25000
b10110010101000011001000011010011 #
b10110010101000011001000011010011 =
b1011110011011110111110011000101 $
b1011110011011110111110011000101 <
b10 ,
1+
#26000
0+
#27000
b11 ,
1+
#28000
0+
#29000
b0 ,
1+
#30000
0+
#31000
b1 .
b1 3
b0 -
b0 2
b1100101010000110010000110100111 "
b1100101010000110010000110100111 5
b1100101010000110010000110100111 1
b10111100110111101111100110001010 !
b10111100110111101111100110001010 4
b10111100110111101111100110001010 0
b1 ,
1+
#32000
0+
#33000
b1100101010000110010000110100111 )
b1100101010000110010000110100111 7
b10111100110111101111100110001010 *
b10111100110111101111100110001010 6
b10 ,
1+
#34000
0+
#35000
b11 ,
1+
#36000
0+
#37000
b0 ,
1+
#38000
0+
#39000
b11 .
b11 3
b10 -
b10 2
b11001010100001100100001101001110 "
b11001010100001100100001101001110 5
b11001010100001100100001101001110 1
b1111001101111011111001100010101 !
b1111001101111011111001100010101 4
b1111001101111011111001100010101 0
b1 ,
1+
#40000
0+
#41000
b11001010100001100100001101001110 '
b11001010100001100100001101001110 9
b1111001101111011111001100010101 (
b1111001101111011111001100010101 8
b10 ,
1+
#42000
0+
#43000
b11 ,
1+
#44000
0+
#45000
b0 ,
1+
#46000
0+
#47000
b101 .
b101 3
b100 -
b100 2
b10010101000011001000011010011101 "
b10010101000011001000011010011101 5
b10010101000011001000011010011101 1
b11110011011110111110011000101010 !
b11110011011110111110011000101010 4
b11110011011110111110011000101010 0
b1 ,
1+
#48000
0+
#49000
b10010101000011001000011010011101 %
b10010101000011001000011010011101 ;
b11110011011110111110011000101010 &
b11110011011110111110011000101010 :
b10 ,
1+
#50000
0+
#51000
b11 ,
1+
#52000
0+
#53000
b0 ,
1+
#54000
0+
#55000
b111 .
b111 3
b110 -
b110 2
b101010000110010000110100111011 "
b101010000110010000110100111011 5
b101010000110010000110100111011 1
b11100110111101111100110001010101 !
b11100110111101111100110001010101 4
b11100110111101111100110001010101 0
b1 ,
1+
#56000
0+
#57000
b101010000110010000110100111011 #
b101010000110010000110100111011 =
b11100110111101111100110001010101 $
b11100110111101111100110001010101 <
b10 ,
1+
#58000
0+
#59000
b11 ,
1+
#60000
0+
#61000
b0 ,
1+
#62000
0+
#63000
b1 .
b1 3
b0 -
b0 2
b1010100001100100001101001110110 "
b1010100001100100001101001110110 5
b1010100001100100001101001110110 1
b11001101111011111001100010101011 !
b11001101111011111001100010101011 4
b11001101111011111001100010101011 0
b1 ,
1+
#64000
0+
#65000
b1010100001100100001101001110110 )
b1010100001100100001101001110110 7
b11001101111011111001100010101011 *
b11001101111011111001100010101011 6
b10 ,
1+
#66000
0+
#67000
b11 ,
1+
#68000
0+
#69000
b0 ,
1+
#70000
0+
#71000
b11 .
b11 3
b10 -
b10 2
b10101000011001000011010011101100 "
b10101000011001000011010011101100 5
b10101000011001000011010011101100 1
b10011011110111110011000101010111 !
b10011011110111110011000101010111 4
b10011011110111110011000101010111 0
b1 ,
1+
#72000
0+
#73000
b10101000011001000011010011101100 '
b10101000011001000011010011101100 9
b10011011110111110011000101010111 (
b10011011110111110011000101010111 8
b10 ,
1+
#74000
0+
#75000
b11 ,
1+
#76000
0+
#77000
b0 ,
1+
#78000
0+
#79000
b101 .
b101 3
b100 -
b100 2
b1010000110010000110100111011001 "
b1010000110010000110100111011001 5
b1010000110010000110100111011001 1
b110111101111100110001010101111 !
b110111101111100110001010101111 4
b110111101111100110001010101111 0
b1 ,
1+
#80000
0+
#81000
b1010000110010000110100111011001 %
b1010000110010000110100111011001 ;
b110111101111100110001010101111 &
b110111101111100110001010101111 :
b10 ,
1+
#82000
0+
#83000
b11 ,
1+
#84000
0+
#85000
b0 ,
1+
#86000
0+
#87000
b111 .
b111 3
b110 -
b110 2
b10100001100100001101001110110010 "
b10100001100100001101001110110010 5
b10100001100100001101001110110010 1
b1101111011111001100010101011110 !
b1101111011111001100010101011110 4
b1101111011111001100010101011110 0
b1 ,
1+
#88000
0+
#89000
b10100001100100001101001110110010 #
b10100001100100001101001110110010 =
b1101111011111001100010101011110 $
b1101111011111001100010101011110 <
b10 ,
1+
#90000
0+
#91000
b11 ,
1+
#92000
0+
#93000
b0 ,
1+
#94000
0+
#95000
b1 .
b1 3
b0 -
b0 2
b1000011001000011010011101100101 "
b1000011001000011010011101100101 5
b1000011001000011010011101100101 1
b11011110111110011000101010111100 !
b11011110111110011000101010111100 4
b11011110111110011000101010111100 0
b1 ,
1+
#96000
0+
#97000
b1000011001000011010011101100101 )
b1000011001000011010011101100101 7
b11011110111110011000101010111100 *
b11011110111110011000101010111100 6
b10 ,
1+
#98000
0+
#99000
b11 ,
1+
#100000
0+
#101000
b0 ,
1+
#102000
0+
#103000
b11 .
b11 3
b10 -
b10 2
b10000110010000110100111011001010 "
b10000110010000110100111011001010 5
b10000110010000110100111011001010 1
b10111101111100110001010101111001 !
b10111101111100110001010101111001 4
b10111101111100110001010101111001 0
b1 ,
1+
#104000
0+
#105000
b10000110010000110100111011001010 '
b10000110010000110100111011001010 9
b10111101111100110001010101111001 (
b10111101111100110001010101111001 8
b10 ,
1+
#106000
0+
#107000
b11 ,
1+
#108000
0+
#109000
b0 ,
1+
#110000
0+
#111000
b101 .
b101 3
b100 -
b100 2
b1100100001101001110110010101 "
b1100100001101001110110010101 5
b1100100001101001110110010101 1
b1111011111001100010101011110011 !
b1111011111001100010101011110011 4
b1111011111001100010101011110011 0
b1 ,
1+
#112000
0+
#113000
b1100100001101001110110010101 %
b1100100001101001110110010101 ;
b1111011111001100010101011110011 &
b1111011111001100010101011110011 :
b10 ,
1+
#114000
0+
#115000
b11 ,
1+
#116000
0+
#117000
b0 ,
1+
#118000
0+
#119000
b111 .
b111 3
b110 -
b110 2
b11001000011010011101100101010 "
b11001000011010011101100101010 5
b11001000011010011101100101010 1
b11110111110011000101010111100110 !
b11110111110011000101010111100110 4
b11110111110011000101010111100110 0
b1 ,
1+
#120000
0+
#121000
b11001000011010011101100101010 #
b11001000011010011101100101010 =
b11110111110011000101010111100110 $
b11110111110011000101010111100110 <
b10 ,
1+
#122000
0+
#123000
b11 ,
1+
#124000
0+
#125000
b0 ,
1+
#126000
0+
#127000
b1 .
b1 3
b0 -
b0 2
b110010000110100111011001010100 "
b110010000110100111011001010100 5
b110010000110100111011001010100 1
b11101111100110001010101111001101 !
b11101111100110001010101111001101 4
b11101111100110001010101111001101 0
b1 ,
1+
#128000
0+
#129000
b110010000110100111011001010100 )
b110010000110100111011001010100 7
b11101111100110001010101111001101 *
b11101111100110001010101111001101 6
b10 ,
1+
#130000
0+
#131000
b11 ,
1+
#132000
0+
#133000
b0 ,
1+
#134000
0+
#135000
b11 .
b11 3
b10 -
b10 2
b1100100001101001110110010101000 "
b1100100001101001110110010101000 5
b1100100001101001110110010101000 1
b11011111001100010101011110011011 !
b11011111001100010101011110011011 4
b11011111001100010101011110011011 0
b1 ,
1+
#136000
0+
#137000
b1100100001101001110110010101000 '
b1100100001101001110110010101000 9
b11011111001100010101011110011011 (
b11011111001100010101011110011011 8
b10 ,
1+
#138000
0+
#139000
b11 ,
1+
#140000
0+
#141000
b0 ,
1+
#142000
0+
#143000
b101 .
b101 3
b100 -
b100 2
b11001000011010011101100101010000 "
b11001000011010011101100101010000 5
b11001000011010011101100101010000 1
b10111110011000101010111100110111 !
b10111110011000101010111100110111 4
b10111110011000101010111100110111 0
b1 ,
1+
#144000
0+
#145000
b11001000011010011101100101010000 %
b11001000011010011101100101010000 ;
b10111110011000101010111100110111 &
b10111110011000101010111100110111 :
b10 ,
1+
#146000
0+
#147000
b11 ,
1+
#148000
0+
#149000
b0 ,
1+
#150000
0+
#151000
b111 .
b111 3
b110 -
b110 2
b10010000110100111011001010100001 "
b10010000110100111011001010100001 5
b10010000110100111011001010100001 1
b1111100110001010101111001101111 !
b1111100110001010101111001101111 4
b1111100110001010101111001101111 0
b1 ,
1+
#152000
0+
#153000
b10010000110100111011001010100001 #
b10010000110100111011001010100001 =
b1111100110001010101111001101111 $
b1111100110001010101111001101111 <
b10 ,
1+
#154000
0+
#155000
b11 ,
1+
#156000
0+
#157000
b0 ,
1+
#158000
0+
#159000
b1 .
b1 3
b0 -
b0 2
b100001101001110110010101000011 "
b100001101001110110010101000011 5
b100001101001110110010101000011 1
b11111001100010101011110011011110 !
b11111001100010101011110011011110 4
b11111001100010101011110011011110 0
b1 ,
1+
#160000
0+
#161000
b100001101001110110010101000011 )
b100001101001110110010101000011 7
b11111001100010101011110011011110 *
b11111001100010101011110011011110 6
b10 ,
1+
#162000
0+
#163000
b11 ,
1+
#164000
0+
#165000
b0 ,
1+
#166000
0+
#167000
b11 .
b11 3
b10 -
b10 2
b1000011010011101100101010000110 "
b1000011010011101100101010000110 5
b1000011010011101100101010000110 1
b11110011000101010111100110111101 !
b11110011000101010111100110111101 4
b11110011000101010111100110111101 0
b1 ,
1+
#168000
0+
#169000
b1000011010011101100101010000110 '
b1000011010011101100101010000110 9
b11110011000101010111100110111101 (
b11110011000101010111100110111101 8
b10 ,
1+
#170000
0+
#171000
b11 ,
1+
#172000
0+
#173000
b0 ,
1+
#174000
0+
#175000
b101 .
b101 3
b100 -
b100 2
b10000110100111011001010100001100 "
b10000110100111011001010100001100 5
b10000110100111011001010100001100 1
b11100110001010101111001101111011 !
b11100110001010101111001101111011 4
b11100110001010101111001101111011 0
b1 ,
1+
#176000
0+
#177000
b10000110100111011001010100001100 %
b10000110100111011001010100001100 ;
b11100110001010101111001101111011 &
b11100110001010101111001101111011 :
b10 ,
1+
#178000
0+
#179000
b11 ,
1+
#180000
0+
#181000
b0 ,
1+
#182000
0+
#183000
b111 .
b111 3
b110 -
b110 2
b1101001110110010101000011001 "
b1101001110110010101000011001 5
b1101001110110010101000011001 1
b11001100010101011110011011110111 !
b11001100010101011110011011110111 4
b11001100010101011110011011110111 0
b1 ,
1+
#184000
0+
#185000
b1101001110110010101000011001 #
b1101001110110010101000011001 =
b11001100010101011110011011110111 $
b11001100010101011110011011110111 <
b10 ,
1+
#186000
0+
#187000
b11 ,
1+
#188000
0+
#189000
b0 ,
1+
#190000
0+
#191000
b1 .
b1 3
b0 -
b0 2
b11010011101100101010000110010 "
b11010011101100101010000110010 5
b11010011101100101010000110010 1
b10011000101010111100110111101111 !
b10011000101010111100110111101111 4
b10011000101010111100110111101111 0
b1 ,
1+
#192000
0+
#193000
b11010011101100101010000110010 )
b11010011101100101010000110010 7
b10011000101010111100110111101111 *
b10011000101010111100110111101111 6
b10 ,
1+
#194000
0+
#195000
b11 ,
1+
#196000
0+
#197000
b0 ,
1+
#198000
0+
#199000
b11 .
b11 3
b10 -
b10 2
b110100111011001010100001100100 "
b110100111011001010100001100100 5
b110100111011001010100001100100 1
b110001010101111001101111011111 !
b110001010101111001101111011111 4
b110001010101111001101111011111 0
b1 ,
1+
#200000
0+
#201000
b110100111011001010100001100100 '
b110100111011001010100001100100 9
b110001010101111001101111011111 (
b110001010101111001101111011111 8
b10 ,
1+
#202000
0+
#203000
b11 ,
1+
