alu.v
//算数逻辑运算单元 alu.v
module alu(
input[31:0]         aluA,
input[31:0]         aluB,
input[3:0]          alufun,
output[31:0]        valE,
output[2:0]         cc
);

wire                ZF, SF, OF;

wire signed[31:0]   A, B, E;
assign              A = aluA;
assign              B = aluB;
assign              E = valE;
assign              cc = {ZF, SF, OF};
assign valE = (alufun == 0) ? (aluA + aluB) : 
              (alufun == 1) ? (aluA - aluB) :
              //(alufun == 2) ? (aluA && aluB):
              //(alufun == 3) ? ((!aluA)&&aluB)||(aluA&&(!aluB)) :
              (alufun == 2) ? (aluA & aluB):
              (alufun == 3) ? ((~aluA)&aluB)|(aluA&(~aluB)) :
              32'bz;

//cc[2] = ZF, cc[1] = SF, cc[0] = OF.
assign ZF = (valE == 0) ? 1'b1 : 1'b0;
assign SF = (valE[31] == 1) ? 1'b1 : 1'b0;
assign OF = (alufun == 1) ? 
            ((((A > 0)&&(B < 0)&&(E <= 0))||((A < 0)&&(B > 0)&&(E >= 0))) ? 1 : 0) : 
             (((A < 0)&&(B < 0)&&(E >= 0))||((A >= 0)&&(B >= 0)&&(E < 0))) ? 1 : 0;

endmodule
/*
//-------Testbench of ALU-------//
module alu_tb;
reg[31:0]       aluA;
reg[31:0]       aluB;
reg[3:0]        alufun;
wire[31:0]      valE;
wire[2:0]       cc;
alu alu(
                aluA,
                aluB,
                alufun,
                valE,
                cc
);
//initial begin
//        alufun <= 0; aluA <= 32'h0AE20D6A; aluB <= 32'h59BB45EB; 
//    #30 alufun <= 1;
//    #30 alufun <= 2;
//    #30 alufun <= 3;
//    #80 $stop;
//end
initial begin
        alufun <= 2; aluA <= 32'h1100; aluB <= 32'h11;
    #20 alufun <= 1; aluA <= 32'h11; aluB <= 32'h133;
    #20 alufun <= 0; aluA <= 32'h7FFED28A; aluB <= 32'h7FFED28A;
    #20 alufun <= 1; aluA <= 32'hEECE2ADD; aluB <= 32'h7EFFC55C;
    #80 $stop;
end
initial begin
    $dumpfile("alu_tb_cc.vcd");
    $dumpvars();
end
endmodule
*/

regfile.v
//寄存器读写文件 regfile.v
`timescale 1ns/10ps
module regfile(
input[3:0]          dstE,
input[31:0]         valE,
input[3:0]          dstM,
input[31:0]         valM,
input[3:0]          rA,
input[3:0]          rB,
input               reset,
input               clock,
output[31:0]        valA,
output[31:0]        valB,
output[31:0]        r0,
output[31:0]        r1,
output[31:0]        r2,
output[31:0]        r3,
output[31:0]        r4,
output[31:0]        r5,
output[31:0]        r6,
output[31:0]        r7
);
reg[31:0]           r_r0, r_r1, r_r2, r_r3, r_r4, r_r5,r_r6, r_r7;
assign              valA = (rA == 0) ? r0 :
                           (rA == 1) ? r1 :
                           (rA == 2) ? r2 :
                           (rA == 3) ? r3 :
                           (rA == 4) ? r4 :
                           (rA == 5) ? r5 :
                           (rA == 6) ? r6 :
                           (rA == 7) ? r7 : 32'bz;
assign              valB = (rB == 0) ? r0 :
                           (rB == 1) ? r1 :
                           (rB == 2) ? r2 :
                           (rB == 3) ? r3 :
                           (rB == 4) ? r4 :
                           (rB == 5) ? r5 :
                           (rB == 6) ? r6 :
                           (rB == 7) ? r7 : 32'bz;
assign              r0   = r_r0;
assign              r1   = r_r1;
assign              r2   = r_r2;
assign              r3   = r_r3;
assign              r4   = r_r4;
assign              r5   = r_r5;
assign              r6   = r_r6;
assign              r7   = r_r7;
always @(posedge clock or negedge reset) begin
    if (reset)begin
        //r_valA <= 0; r_valB <= 0;
        r_r0 <= 0; r_r1 <= 0; r_r2 <= 0; r_r3 <= 0; 
        r_r4 <= 0; r_r5 <= 0; r_r6 <= 0; r_r7 <= 0; 
    end
    else begin
        case(dstE)
            0: begin r_r0 <= valE; end
            1: begin r_r1 <= valE; end
            2: begin r_r2 <= valE; end
            3: begin r_r3 <= valE; end
            4: begin r_r4 <= valE; end
            5: begin r_r5 <= valE; end
            6: begin r_r6 <= valE; end
            7: begin r_r7 <= valE; end
        endcase
        case(dstM)
            0: begin r_r0 <= valM; end
            1: begin r_r1 <= valM; end
            2: begin r_r2 <= valM; end
            3: begin r_r3 <= valM; end
            4: begin r_r4 <= valM; end
            5: begin r_r5 <= valM; end
            6: begin r_r6 <= valM; end
            7: begin r_r7 <= valM; end
        endcase
    end
end
endmodule

/*
module regfile_tb;
reg[3:0]          dstE;
reg[3:0]          dstM;
wire[31:0]        valE;
wire[31:0]        valM;
reg[3:0]          rA;
reg[3:0]          rB;
reg               reset;
reg               clock;
wire[31:0]        r0;
wire[31:0]        r1;
wire[31:0]        r2;
wire[31:0]        r3;
wire[31:0]        r4;
wire[31:0]        r5;
wire[31:0]        r6;
wire[31:0]        r7;

reg[31:0]         write_bufferE;
reg[31:0]         write_bufferM;
reg[12:0]         con;
assign            valE = write_bufferE;
assign            valM = write_bufferM;
regfile regfile(
                  dstE,
                  valE,
                  dstM,
                  valM,
                  rA,
                  rB,
                  reset,
                  clock,
                  valA,
                  valB,
                  r0, r1, r2, r3, r4, r5, r6, r7
);
initial begin
            clock <= 0; reset <= 1;
            dstE <= 0;  dstM <= 1; con <= 1;
            write_bufferE <= 32'hABCDEF98;
            write_bufferM <= 32'h7654321A;
    #37     reset <= 0;
    #2000   $stop;
end
always #10 clock = ~clock;
always @(posedge clock) begin
    if (con == 4-1)begin
        con <= 0;
    end
    else begin
        con <= con+1;
    end
    if (con == 0)begin
        write_bufferE[31:1] <= write_bufferE[30:0];
        write_bufferE[0]    <= write_bufferE[31];
        write_bufferM[31:1] <= write_bufferM[30:0];
        write_bufferM[0]    <= write_bufferM[31];
        dstE <= dstE + 2; dstM <= dstM + 2;
        if (dstE == 6)begin
            dstE <= 0;
        end
        if (dstM == 7)begin
            dstM <= 1;
        end
    end
end
initial begin
    $dumpfile("regfile_tb.vcd");
    $dumpvars;
end
endmodule */

ram.v
//存储器文件ram.v
`timescale 1ns/10ps
module ram(
input               clock,
input[8:0]          addr,
input               wr,
input[31:0]         wdata,
input               rd,
output reg[31:0]    rdata
);

reg[31:0]           ram[127:0];   //RAM
always @(negedge clock) begin
    if (wr)begin
        ram[addr] <= wdata;       //向RAM中写入数据
    end
    if (rd) begin
        rdata <= ram[addr];       //从RAM中读取数据
    end
    else begin
        rdata <= 32'bz;           //读写均无效时，为高阻态。
    end
end
endmodule

//-----Testbench of ram-------//
module ram_tb;
reg             clock;
reg[8:0]        addr;
reg             wr, rd;
reg[31:0]       wdata;
wire[31:0]      rdata;

reg[63:0]       data_buffer;
reg[15:0]       addr_buffer;
ram ram(
                clock,
                addr,
                wr,
                wdata,
                rd,
                rdata
);
initial begin
    clock <= 0; rd <= 0; wr <= 0; wdata <= 0; addr <= 0;
    data_buffer[63:32] = {4'h2, 4'h2, 4'h4, 4'h5, 8'h0, 8'h0}; 
    data_buffer[31:0]  = {4'h1, 4'h0, 4'hf, 4'h0, 4'h0, 4'h0, 4'h1, 4'h0};
    addr_buffer[15:0]  = {8'h0, 8'h1};
    #10   addr <= addr_buffer[15:8]; wr <= 1; wdata <= data_buffer[63:32];
    #400  wr <= 0;
    #500  addr <= addr_buffer[7:0];  wr <= 1; wdata <= data_buffer[31:0];
    #900  addr <= addr_buffer[15:8]; wr <= 0; wdata <= 0; 
    #1000 rd <= 1;
    #1200 rd <= 0; addr <= addr_buffer[7:0];
    #1500 rd <= 1;
    #1900 rd <= 0;
    #2000 $stop;
end
always #5 clock <= ~clock;
initial begin
    $dumpfile("tb/ram_tb.vcd");
    $dumpvars(addr, wr, rd, wdata, rdata, addr);
end
endmodule

processor.v
//处理器Z的顶层文件 processor.v
`timescale 1ns/10ps
module processor(
input           clock,
input[8:0]      addr,
input           wr,
input[31:0]     wdata,
input           working,
//output[31:0]    valA,
//output[31:0]    valB,
output[31:0]    valE,
output[31:0]    r0,
output[31:0]    r1,
output[31:0]    r2,
output[31:0]    r3,
output[31:0]    r4,
output[31:0]    r5,
output[31:0]    r6,
output[31:0]    r7
//output[3:0]     icode,
//output[3:0]     ifun,
//output[3:0]     rA,
//output[3:0]     rB,
//output[15:0]    valC
);
parameter IRMOV = 8'h10;
parameter ADD   = 8'h20;
parameter SUB   = 8'h21;
parameter AND   = 8'h22;
parameter XOR   = 8'h23;
ram ram(
                .clock(clock),
                .addr(addr_w),
                .wr(wr),
                .wdata(wdata),
                .rd(rd),
                .rdata(rdata)
);
regfile regfile(
                .dstE(w_dstE),
                .valE(w_valE),
                .dstM(w_dstM),
                .valM(w_valM),
                .rA(d_rA),
                .rB(d_rB),
                .reset(e_reg_rst),
                .clock(clock),
                .valA(d_valA),
                .valB(d_valB),
                .r0(r0),
                .r1(r1),
                .r2(r2),
                .r3(r3),
                .r4(r4),
                .r5(r5),
                .r6(r6),
                .r7(r7)
);
alu alu(
                .aluA(e_valA),
                .aluB(e_valB),
                .alufun(e_alufun),
                .valE(e_valE)
);
//-----Fetch stage signals-----//
reg[8:0]        PC = 0;
wire[8:0]       addr_w;
wire            rd;
wire[31:0]      rdata;
wire[31:0]      F_read;
//------------Fetch--------------//
assign addr_w = (working) ? PC   : addr;
assign rd     = (working) ? 1    : 0;
assign F_read = rdata;
always @(posedge clock) begin
    if (working)begin
        PC <= PC + 1;
    end
end

//------Decode stage signals-----//
reg[3:0]        d_icode = 4'bz;
reg[3:0]        d_ifun  = 4'bz;
reg[3:0]        d_rA    = 4'bz;
reg[3:0]        d_rB    = 4'bz;
reg[15:0]       d_valC  = 16'bz;
wire[31:0]      d_valA  = 32'bz;
wire[31:0]      d_valB  = 32'bz;
reg[3:0]        D_icode = 4'bz;
reg[3:0]        D_ifun  = 4'bz;
reg[3:0]        D_rA    = 4'bz;
reg[3:0]        D_rB    = 4'bz;
reg[31:0]       D_valA  = 32'bz;
reg[31:0]       D_valB  = 32'bz;
reg[15:0]       D_valC  = 16'bz;
//-------------Decode------------//
//assign icode  = D_icode;
//assign ifun   = D_ifun;
//assign rA     = D_rB;
//assign rB     = D_rB;
//assign valC   = D_valC;
//assign valA     = d_valA;
//assign valB     = d_valB;
//assign d_rA     = D_rA;
//assign d_rB     = D_rB;         
always @(posedge clock) begin
    if (working)begin
        d_icode <= F_read[31:28];
        d_ifun  <= F_read[27:24];
        d_rA    <= F_read[23:20];
        d_rB    <= F_read[19:16];
        d_valC  <= F_read[15: 0];
        D_icode <= d_icode;
        D_ifun  <= d_ifun;
        D_rA    <= d_rA;
        D_rB    <= d_rB;
        D_valC  <= d_valC;
        D_valA  <= d_valA;
        D_valB  <= d_valB;
    end
end

//------Execute stage signals-----//
reg[3:0]          E_dstM = 4'bz;
reg[31:0]         E_valM = 32'bz;
reg               e_reg_rst;
wire[31:0]        e_valA = 32'bz;
wire[31:0]        e_valB = 32'bz;
wire[3:0]         e_alufun = 4'bz;
wire[31:0]        e_valE = 32'bz;
reg[3:0]          E_dstE = 4'bz;
reg[31:0]         E_valE = 32'bz;
initial begin
        e_reg_rst <= 1;
    #20 e_reg_rst <= 0;
end
//----------Execute stage---------//
assign            valE   = e_valE; 
assign            e_valA = D_valA;
assign            e_valB = D_valB;
assign            e_alufun = 
                  ({D_icode, D_ifun} == ADD) ? 0 :
                  ({D_icode, D_ifun} == SUB) ? 1 :
                  ({D_icode, D_ifun} == AND) ? 2 :
                  ({D_icode, D_ifun} == XOR) ? 3 : 4'bz;
always @(posedge clock) begin
    if ({D_icode, D_ifun} == IRMOV)begin
        E_dstM <= D_rB;
        E_valM <= D_valC;
    end
    E_dstE <= D_rA;
    E_valE <= e_valE;
end

//----Write-back stage signals----//
reg[3:0]          w_dstM = 4'bz;
reg[31:0]         w_valM = 32'bz;
reg[3:0]          w_dstE = 4'bz;
reg[31:0]         w_valE = 32'bz;
//-----------Write-back-----------//
always @(posedge clock) begin
        w_dstM <= E_dstM;
        w_valM <= E_valM;
        w_dstE <= E_dstE;
        w_valE <= E_valE;
end
endmodule


//-----Testbench of processor-----//
module pro_tb4;
reg             clock;
reg[8:0]        addr;
reg             wr;
reg[31:0]       wdata;
reg             working;
//wire[31:0]      valA, valB; 
wire[31:0]      valE;
wire[31:0]      r0, r1, r2, r3, r4, r5, r6, r7;
//wire[3:0]       icode;
//wire[3:0]       ifun;
//wire[3:0]       rA;
//wire[3:0]       rB;
//wire[15:0]      valC;
//wire[31:0]      valE;
processor processor(
                clock,
                addr,
                wr,
                wdata,
                working,
                //icode,
                //ifun,
                //rA,
                //rB,
                //valC,
                //valA,
                //valB,
                valE,
                r0, r1, r2, r3, r4, r5, r6, r7
                //valE
);
initial begin
    clock <= 0; addr <= 0; wr <= 0; wdata <= 0; working <= 0;
    #20         addr <= 0; wr <= 1; wdata <= 32'h10F00080;
    #20         addr <= 1; wr <= 1; wdata <= 32'h10F10081;
    #20         addr <= 2; wr <= 1; wdata <= 32'h10F20082;
    #20         addr <= 3; wr <= 1; wdata <= 32'h10F30083;
    #20         addr <= 4; wr <= 1; wdata <= 32'h10F40084;
    #20         addr <= 5; wr <= 1; wdata <= 32'h10F50085;
    #20         addr <= 6; wr <= 1; wdata <= 32'h10F60086;
    #20         addr <= 7; wr <= 1; wdata <= 32'h10F70087;
    #20         addr <= 8; wr <= 1; wdata <= 32'h20010000;
    #20         addr <= 9; wr <= 1; wdata <= 32'h21230000;
    #20         addr <= 10;wr <= 1; wdata <= 32'h22450000;
    #20         addr <= 11;wr <= 1; wdata <= 32'h23670000;
    #20         addr <= 0; wr <= 0; wdata <= 0;
    #10         working <= 1;
    #500        $stop;
end
always #10 clock = ~clock;
initial begin
    $dumpfile("tb/pro_tb4.vcd");
    $dumpvars();
end
endmodule


/*
//-----Testbench of processor (Task 1)-------//
module pro_tb;
reg             clock;
reg[8:0]        addr;
reg             wr;
reg[31:0]       wdata;
reg             working;
wire[3:0]       icode;
wire[3:0]       ifun;
wire[3:0]       rA;
wire[3:0]       rB;
wire[15:0]      valC; 
processor processor(
                clock,
                addr,
                wr,
                wdata,
                working,
                icode,
                ifun,
                rA,
                rB,
                valC
);
initial begin
    clock <= 0; addr <= 0; wdata <= 32'h00000000; wr <= 0; working <= 0;
    #20         addr <= 0; wdata <= 32'h10f00010; wr <= 1;
    #20         addr <= 1; wdata <= 32'h20010000;
    #20         addr <= 2; wdata <= 32'h21230000;
    #20         addr <= 3; wdata <= 32'h22450000;
    #20         addr <= 4; wdata <= 32'h23670000;
    #20         addr <= 0; wdata <= 32'h00000000; wr <= 0; working <= 1;
    //#20         working <= 1;
    #150        $stop;
end
always #10 clock = ~clock;
initial begin
    $dumpfile("pro_tb.vcd");
    $dumpvars;
end
endmodule*/

/*module processor(
input           clock,
input[8:0]      addr,
input           wr,
input[31:0]     wdata,
input           working,
output[3:0]     icode,
output[3:0]     ifun,
output[3:0]     rA,
output[3:0]     rB,
output[15:0]    valC,
//output[15:0]    valD, /////////
output[31:0]    r0,
output[31:0]    r1,
output[31:0]    r2,
output[31:0]    r3,
output[31:0]    r4,
output[31:0]    r5,
output[31:0]    r6,
output[31:0]    r7,
output[31:0]    valA,
output[31:0]    valB,
output[31:0]    valE
);

//wire            read = 0;
//reg[8:0]       addr_buffer;
//reg[31:0]      read_buffer = 0;
//assign icode = read_buffer[31:28];
//assign ifun  = read_buffer[27:24];
//assign rA    = read_buffer[23:20];
//assign rB    = read_buffer[19:16];
//assign valC  = read_buffer[15: 0];

wire[8:0]       addr_w;
wire[31:0]      read_w;
reg[8:0]        PC = 0;
reg             read = 0; //3
reg[3:0]        dstE_reg = 4'hF;
reg[3:0]        dstM = 0;
reg[31:0]       valM = 0;
reg[15:0]       valC;
reg             reg_rst;
wire[31:0]      aluA;
wire[31:0]      aluB;
reg[3:0]        alufun;
wire[31:0]      aluValE;
// Separate instruction fetching and decoding
// adding a pipeline
reg[3:0]        icode;
reg[3:0]        ifun;
reg[3:0]        rA;
reg[3:0]        rB;
//assign icode  = read_w[31:28];
//assign ifun   = read_w[27:24];
//assign rA     = read_w[23:20];
//assign rB     = read_w[19:16];
//
assign addr_w = (working) ? PC : addr;
assign aluA   = valA;
assign aluB   = valB;
assign valE   = aluValE;
//assign valE_reg = valE;
//assign valC   = read_w[15: 0];
//assign read   = (working) ? 1  : 0;

ram ram(
                .clock(clock),
                .addr(addr_w),
                .wr(wr),
                .wdata(wdata),
                .rd(read),
                .rdata(read_w)
);
regfile regfile(
                .dstE(dstE_reg),
                .valE(aluValE),
                .dstM(dstM),
                .valM(valM),
                .rA(rA),
                .rB(rB),
                .reset(reg_rst),
                .clock(clock),
                .r0(r0),
                .r1(r1),
                .r2(r2),
                .r3(r3),
                .r4(r4),
                .r5(r5),
                .r6(r6),
                .r7(r7),
                .valA(valA),
                .valB(valB)
);
alu alu(
        .aluA(aluA),
        .aluB(aluB),
        .alufun(alufun),
        .valE(aluValE)
);

initial begin
        reg_rst <= 1;
    #20 reg_rst <= 0;
end

always @(posedge clock) begin
    if(working)begin
        //addr_w <= PC;
        //read_buffer <= read_w;
        read = 1; 
        PC <= PC+1;
        icode <= read_w[31:28];
        ifun  <= read_w[27:24];
        valC  <= read_w[15: 0];//////////
        rA    <= read_w[23:20];
        rB    <= read_w[19:16];
        case(read_w[31:24])
            8'h10: begin
                dstM <= read_w[19:16];
                valM <= read_w[15: 0]; 
            end            
            8'h20: begin
                alufun <= 0;
                dstE_reg <= rA;
                //valE_reg <= valE;
            end
            8'h21: begin
                alufun <= 1;
                dstE_reg <= rA;
                //valE_reg <= valE;
            end
            8'h22: begin
                alufun <= 2;
                dstE_reg <= rA;
               //valE_reg <= valE;
            end
            8'h23: begin
                alufun <= 3;
                dstE_reg <= rA;
               //valE_reg <= valE;
            end
        endcase
    end
    else begin
        if (wr)begin
        read = 0; //
        //addr_w <= addr;
        //read_buffer <= read_w;
        //icode <= read_buffer[31:28];
        end
    end
end
endmodule

module pro_tb2;
reg             clock;
reg[8:0]        addr;
reg             wr;
reg[31:0]       wdata;
reg             working;
wire[3:0]       icode;
wire[3:0]       ifun;
wire[3:0]       rA;
wire[3:0]       rB;
wire[15:0]      valC;
//wire[15:0]      valD;/////////
wire[31:0]      valB, valA; 
wire[31:0]      r0, r1, r2, r3, r4, r5, r6, r7;
wire[31:0]      valE;
processor processor(
                clock,
                addr,
                wr,
                wdata,
                working,
                icode,
                ifun,
                rA,
                rB,
                valC,
                r0, r1, r2, r3, r4, r5, r6, r7,
                valA,
                valB,
                valE
);
initial begin
    clock <= 0; addr <= 0; wr <= 0; wdata <= 0; working <= 0;
    #20         addr <= 0; wr <= 1; wdata <= 32'h10F00080;
    #20         addr <= 1; wr <= 1; wdata <= 32'h10F10081;
    #20         addr <= 2; wr <= 1; wdata <= 32'h10F20082;
    #20         addr <= 3; wr <= 1; wdata <= 32'h10F30083;
    #20         addr <= 4; wr <= 1; wdata <= 32'h10F40084;
    #20         addr <= 5; wr <= 1; wdata <= 32'h10F50085;
    #20         addr <= 6; wr <= 1; wdata <= 32'h10F60086;
    #20         addr <= 7; wr <= 1; wdata <= 32'h10F70087;
    #20         addr <= 8; wr <= 1; wdata <= 32'h20010000;
    #20         addr <= 9; wr <= 1; wdata <= 32'h21230000;
    #20         addr <= 10;wr <= 1; wdata <= 32'h22450000;
    #20         addr <= 11;wr <= 1; wdata <= 32'h23670000;
    #20         addr <= 0; wr <= 0; wdata <= 0;
    #10         working <= 1;
    #500        $stop;
end
always #10 clock = ~clock;
initial begin
    $dumpfile("tb/pro_tb4.vcd");
    $dumpvars();
end
endmodule
*/

tb/Pics/Task4/pro_tb4.vcd
$date
	Tue May 31 18:39:26 2022
$end
$version
	Icarus Verilog
$end
$timescale
	10ps
$end
$scope module pro_tb4 $end
$var wire 32 ! valE [31:0] $end
$var wire 32 " r7 [31:0] $end
$var wire 32 # r6 [31:0] $end
$var wire 32 $ r5 [31:0] $end
$var wire 32 % r4 [31:0] $end
$var wire 32 & r3 [31:0] $end
$var wire 32 ' r2 [31:0] $end
$var wire 32 ( r1 [31:0] $end
$var wire 32 ) r0 [31:0] $end
$var reg 9 * addr [8:0] $end
$var reg 1 + clock $end
$var reg 32 , wdata [31:0] $end
$var reg 1 - working $end
$var reg 1 . wr $end
$scope module processor $end
$var wire 32 / F_read [31:0] $end
$var wire 9 0 addr [8:0] $end
$var wire 1 + clock $end
$var wire 32 1 e_valA [31:0] $end
$var wire 32 2 e_valB [31:0] $end
$var wire 32 3 valE [31:0] $end
$var wire 32 4 wdata [31:0] $end
$var wire 1 - working $end
$var wire 1 . wr $end
$var wire 32 5 rdata [31:0] $end
$var wire 1 6 rd $end
$var wire 32 7 r7 [31:0] $end
$var wire 32 8 r6 [31:0] $end
$var wire 32 9 r5 [31:0] $end
$var wire 32 : r4 [31:0] $end
$var wire 32 ; r3 [31:0] $end
$var wire 32 < r2 [31:0] $end
$var wire 32 = r1 [31:0] $end
$var wire 32 > r0 [31:0] $end
$var wire 32 ? e_valE [31:0] $end
$var wire 4 @ e_alufun [3:0] $end
$var wire 32 A d_valB [31:0] $end
$var wire 32 B d_valA [31:0] $end
$var wire 9 C addr_w [8:0] $end
$var reg 4 D D_icode [3:0] $end
$var reg 4 E D_ifun [3:0] $end
$var reg 4 F D_rA [3:0] $end
$var reg 4 G D_rB [3:0] $end
$var reg 32 H D_valA [31:0] $end
$var reg 32 I D_valB [31:0] $end
$var reg 16 J D_valC [15:0] $end
$var reg 4 K E_dstE [3:0] $end
$var reg 4 L E_dstM [3:0] $end
$var reg 32 M E_valE [31:0] $end
$var reg 32 N E_valM [31:0] $end
$var reg 9 O PC [8:0] $end
$var reg 4 P d_icode [3:0] $end
$var reg 4 Q d_ifun [3:0] $end
$var reg 4 R d_rA [3:0] $end
$var reg 4 S d_rB [3:0] $end
$var reg 16 T d_valC [15:0] $end
$var reg 1 U e_reg_rst $end
$var reg 4 V w_dstE [3:0] $end
$var reg 4 W w_dstM [3:0] $end
$var reg 32 X w_valE [31:0] $end
$var reg 32 Y w_valM [31:0] $end
$scope module alu $end
$var wire 32 Z aluA [31:0] $end
$var wire 32 [ aluB [31:0] $end
$var wire 4 \ alufun [3:0] $end
$var wire 32 ] valE [31:0] $end
$upscope $end
$scope module ram $end
$var wire 9 ^ addr [8:0] $end
$var wire 1 + clock $end
$var wire 1 6 rd $end
$var wire 32 _ wdata [31:0] $end
$var wire 1 . wr $end
$var reg 32 ` rdata [31:0] $end
$upscope $end
$scope module regfile $end
$var wire 1 + clock $end
$var wire 4 a dstE [3:0] $end
$var wire 4 b dstM [3:0] $end
$var wire 4 c rA [3:0] $end
$var wire 4 d rB [3:0] $end
$var wire 1 U reset $end
$var wire 32 e valE [31:0] $end
$var wire 32 f valM [31:0] $end
$var wire 32 g valB [31:0] $end
$var wire 32 h valA [31:0] $end
$var wire 32 i r7 [31:0] $end
$var wire 32 j r6 [31:0] $end
$var wire 32 k r5 [31:0] $end
$var wire 32 l r4 [31:0] $end
$var wire 32 m r3 [31:0] $end
$var wire 32 n r2 [31:0] $end
$var wire 32 o r1 [31:0] $end
$var wire 32 p r0 [31:0] $end
$var reg 32 q r_r0 [31:0] $end
$var reg 32 r r_r1 [31:0] $end
$var reg 32 s r_r2 [31:0] $end
$var reg 32 t r_r3 [31:0] $end
$var reg 32 u r_r4 [31:0] $end
$var reg 32 v r_r5 [31:0] $end
$var reg 32 w r_r6 [31:0] $end
$var reg 32 x r_r7 [31:0] $end
$upscope $end
$upscope $end
$upscope $end
$enddefinitions $end
#0
$dumpvars
bx x
bx w
bx v
bx u
bx t
bx s
bx r
bx q
bx p
bx o
bx n
bx m
bx l
bx k
bx j
bx i
bx h
bx g
bz f
bz e
bz d
bz c
bz b
bz a
bz `
b0 _
b0 ^
bx ]
bx \
bz [
bz Z
bz Y
bz X
bz W
bz V
1U
bz T
bz S
bz R
bz Q
bz P
b0 O
bz N
bz M
bz L
bz K
bz J
bz I
bz H
bz G
bz F
bz E
bz D
b0 C
bx B
bx A
bx @
bx ?
bx >
bx =
bx <
bx ;
bx :
bx 9
bx 8
bx 7
06
bz 5
b0 4
bx 3
bz 2
bz 1
b0 0
bz /
0.
0-
b0 ,
0+
b0 *
bx )
bx (
bx '
bx &
bx %
bx $
bx #
bx "
bx !
$end
#1000
bx M
b0 "
b0 7
b0 i
b0 x
b0 #
b0 8
b0 j
b0 w
b0 $
b0 9
b0 k
b0 v
b0 %
b0 :
b0 l
b0 u
b0 &
b0 ;
b0 m
b0 t
b0 '
b0 <
b0 n
b0 s
b0 (
b0 =
b0 o
b0 r
b0 )
b0 >
b0 p
b0 q
1+
#2000
b10000111100000000000010000000 ,
b10000111100000000000010000000 4
b10000111100000000000010000000 _
1.
0U
0+
#3000
bx X
bx e
1+
#4000
b1 C
b1 ^
b10000111100010000000010000001 ,
b10000111100010000000010000001 4
b10000111100010000000010000001 _
b1 *
b1 0
0+
#5000
1+
#6000
b10 C
b10 ^
b10000111100100000000010000010 ,
b10000111100100000000010000010 4
b10000111100100000000010000010 _
b10 *
b10 0
0+
#7000
1+
#8000
b11 C
b11 ^
b10000111100110000000010000011 ,
b10000111100110000000010000011 4
b10000111100110000000010000011 _
b11 *
b11 0
0+
#9000
1+
#10000
b100 C
b100 ^
b10000111101000000000010000100 ,
b10000111101000000000010000100 4
b10000111101000000000010000100 _
b100 *
b100 0
0+
#11000
1+
#12000
b101 C
b101 ^
b10000111101010000000010000101 ,
b10000111101010000000010000101 4
b10000111101010000000010000101 _
b101 *
b101 0
0+
#13000
1+
#14000
b110 C
b110 ^
b10000111101100000000010000110 ,
b10000111101100000000010000110 4
b10000111101100000000010000110 _
b110 *
b110 0
0+
#15000
1+
#16000
b111 C
b111 ^
b10000111101110000000010000111 ,
b10000111101110000000010000111 4
b10000111101110000000010000111 _
b111 *
b111 0
0+
#17000
1+
#18000
b1000 C
b1000 ^
b100000000000010000000000000000 ,
b100000000000010000000000000000 4
b100000000000010000000000000000 _
b1000 *
b1000 0
0+
#19000
1+
#20000
b1001 C
b1001 ^
b100001001000110000000000000000 ,
b100001001000110000000000000000 4
b100001001000110000000000000000 _
b1001 *
b1001 0
0+
#21000
1+
#22000
b1010 C
b1010 ^
b100010010001010000000000000000 ,
b100010010001010000000000000000 4
b100010010001010000000000000000 _
b1010 *
b1010 0
0+
#23000
1+
#24000
b1011 C
b1011 ^
b100011011001110000000000000000 ,
b100011011001110000000000000000 4
b100011011001110000000000000000 _
b1011 *
b1011 0
0+
#25000
1+
#26000
b0 C
b0 ^
b0 ,
b0 4
b0 _
0.
b0 *
b0 0
0+
#27000
16
1-
1+
#28000
0+
#29000
b1 C
b1 ^
b10000111100000000000010000000 /
b10000111100000000000010000000 5
b10000111100000000000010000000 `
b1 O
bx 2
bx I
bx [
bx 1
bx H
bx Z
1+
#30000
0+
#31000
b0 A
b0 g
bz B
bz h
b10 C
b10 ^
b10000000 T
b0 S
b0 d
b1111 R
b1111 c
b0 Q
b1 P
b10 O
b10000111100010000000010000001 /
b10000111100010000000010000001 5
b10000111100010000000010000001 `
1+
#32000
0+
#33000
b11 C
b11 ^
bz @
bz \
b10000111100100000000010000010 /
b10000111100100000000010000010 5
b10000111100100000000010000010 `
b11 O
b0 2
b0 I
b0 [
bz 1
bz H
bz Z
b10000000 J
b0 G
b1111 F
b0 E
b1 D
b10000001 T
b1 S
b1 d
1+
#34000
0+
#35000
b100 C
b100 ^
b1111 K
b10000000 N
b0 L
b10000001 J
b1 G
b10000010 T
b10 S
b10 d
b100 O
b10000111100110000000010000011 /
b10000111100110000000010000011 5
b10000111100110000000010000011 `
1+
#36000
0+
#37000
b101 C
b101 ^
b10000111101000000000010000100 /
b10000111101000000000010000100 5
b10000111101000000000010000100 `
b101 O
b10000010 J
b10 G
b10000011 T
b11 S
b11 d
b10000001 N
b1 L
b1111 V
b1111 a
b10000000 Y
b10000000 f
b0 W
b0 b
1+
#38000
0+
#39000
b110 C
b110 ^
b10000001 Y
b10000001 f
b1 W
b1 b
b10000010 N
b10 L
b10000011 J
b11 G
b10000100 T
b100 S
b100 d
b110 O
b10000111101010000000010000101 /
b10000111101010000000010000101 5
b10000111101010000000010000101 `
b10000000 )
b10000000 >
b10000000 p
b10000000 q
1+
#40000
0+
#41000
b111 C
b111 ^
b10000111101100000000010000110 /
b10000111101100000000010000110 5
b10000111101100000000010000110 `
b111 O
b10000100 J
b100 G
b10000101 T
b101 S
b101 d
b10000011 N
b11 L
b10000010 Y
b10000010 f
b10 W
b10 b
b10000001 (
b10000001 =
b10000001 o
b10000001 r
1+
#42000
0+
#43000
b1000 C
b1000 ^
b10000011 Y
b10000011 f
b11 W
b11 b
b10000100 N
b100 L
b10000101 J
b101 G
b10000110 T
b110 S
b110 d
b1000 O
b10000111101110000000010000111 /
b10000111101110000000010000111 5
b10000111101110000000010000111 `
b10000010 '
b10000010 <
b10000010 n
b10000010 s
1+
#44000
0+
#45000
b1001 C
b1001 ^
b100000000000010000000000000000 /
b100000000000010000000000000000 5
b100000000000010000000000000000 `
b1001 O
b10000110 J
b110 G
b10000111 T
b111 S
b111 d
b10000101 N
b101 L
b10000100 Y
b10000100 f
b100 W
b100 b
b10000011 &
b10000011 ;
b10000011 m
b10000011 t
1+
#46000
0+
#47000
b10000001 A
b10000001 g
b10000000 B
b10000000 h
b1010 C
b1010 ^
b10000101 Y
b10000101 f
b101 W
b101 b
b10000110 N
b110 L
b10000111 J
b111 G
b0 T
b1 S
b1 d
b0 R
b0 c
b10 P
b1010 O
b100001001000110000000000000000 /
b100001001000110000000000000000 5
b100001001000110000000000000000 `
b10000100 %
b10000100 :
b10000100 l
b10000100 u
1+
#48000
0+
