ram.v
//存储器文件ram.v
`timescale 1ns/10ps
module ram(
input               clock,
input[8:0]          addr,
input               wr,
input[31:0]         wdata,
input               rd,
output reg[31:0]    rdata
);

reg[31:0]           ram[127:0];   //RAM
always @(negedge clock) begin
    if (wr)begin
        ram[addr] <= wdata;       //向RAM中写入数据
    end
    if (rd) begin
        rdata <= ram[addr];       //从RAM中读取数据
    end
    else begin
        rdata <= 32'bz;           //读写均无效时，为高阻态。
    end
end
endmodule

//-----Testbench of ram-------//
module ram_tb;
reg             clock;
reg[8:0]        addr;
reg             wr, rd;
reg[31:0]       wdata;
wire[31:0]      rdata;

reg[63:0]       data_buffer;
reg[15:0]       addr_buffer;
ram ram(
                clock,
                addr,
                wr,
                wdata,
                rd,
                rdata
);
initial begin
    clock <= 0; rd <= 0; wr <= 0; wdata <= 0; addr <= 0;
    data_buffer[63:32] = {4'h2, 4'h2, 4'h4, 4'h5, 8'h0, 8'h0}; 
    data_buffer[31:0]  = {4'h1, 4'h0, 4'hf, 4'h0, 4'h0, 4'h0, 4'h1, 4'h0};
    addr_buffer[15:0]  = {8'h0, 8'h1};
    #10   addr <= addr_buffer[15:8]; wr <= 1; wdata <= data_buffer[63:32];
    #400  wr <= 0;
    #500  addr <= addr_buffer[7:0];  wr <= 1; wdata <= data_buffer[31:0];
    #900  addr <= addr_buffer[15:8]; wr <= 0; wdata <= 0; 
    #1000 rd <= 1;
    #1200 rd <= 0; addr <= addr_buffer[7:0];
    #1500 rd <= 1;
    #1900 rd <= 0;
    #2000 $stop;
end
always #5 clock <= ~clock;
initial begin
    $dumpfile("tb/ram_tb.vcd");
    $dumpvars(addr, wr, rd, wdata, rdata, addr);
end
endmodule

processor.v
//处理器Z的顶层文件 processor.v
`timescale 1ns/10ps
module processor(
input           clock,
input[8:0]      addr,
input           wr,
input[31:0]     wdata,
input           working,
output[3:0]     icode,
output[3:0]     ifun,
output[3:0]     rA,
output[3:0]     rB,
output[15:0]    valC
);
ram ram(
                .clock(clock),
                .addr(addr_w),
                .wr(wr),
                .wdata(wdata),
                .rd(rd),
                .rdata(rdata)
);
//-----Fetch stage signals-----//
reg[8:0]        PC = 0;
wire[8:0]       addr_w;
wire            rd;
wire[31:0]      rdata;
wire[31:0]      F_read;
//-----------Fetch-------------//
assign addr_w = (working) ? PC   : addr;
assign rd     = (working) ? 1    : 0;
assign F_read = rdata;
always @(posedge clock) begin
    if (working)begin
        PC <= PC + 1;
    end
end
//-------Decoding------//
assign icode  = F_read[31:28];
assign ifun   = F_read[27:24];
assign rA     = F_read[23:20];
assign rB     = F_read[19:16];
assign valC   = F_read[15: 0];
endmodule





//-----Testbench of processor (Task 1)-------//
module pro_tb;
reg             clock;
reg[8:0]        addr;
reg             wr;
reg[31:0]       wdata;
reg             working;
wire[3:0]       icode;
wire[3:0]       ifun;
wire[3:0]       rA;
wire[3:0]       rB;
wire[15:0]      valC; 
processor processor(
                clock,
                addr,
                wr,
                wdata,
                working,
                icode,
                ifun,
                rA,
                rB,
                valC
);
initial begin
    clock <= 0; addr <= 0; wdata <= 32'h00000000; wr <= 0; working <= 0;
    #20         addr <= 0; wdata <= 32'h10f00010; wr <= 1;
    #20         addr <= 1; wdata <= 32'h20010000;
    #20         addr <= 2; wdata <= 32'h21230000;
    #20         addr <= 3; wdata <= 32'h22450000;
    #20         addr <= 4; wdata <= 32'h23670000;
    #20         addr <= 0; wdata <= 32'h00000000; wr <= 0; working <= 1;
    //#20         working <= 1;
    #150        $stop;
end
always #10 clock = ~clock;
initial begin
    $dumpfile("pro_tb.vcd");
    $dumpvars;
end
endmodule

/*module processor(
input           clock,
input[8:0]      addr,
input           wr,
input[31:0]     wdata,
input           working,
output[3:0]     icode,
output[3:0]     ifun,
output[3:0]     rA,
output[3:0]     rB,
output[15:0]    valC,
//output[15:0]    valD, /////////
output[31:0]    r0,
output[31:0]    r1,
output[31:0]    r2,
output[31:0]    r3,
output[31:0]    r4,
output[31:0]    r5,
output[31:0]    r6,
output[31:0]    r7,
output[31:0]    valA,
output[31:0]    valB,
output[31:0]    valE
);

//wire            read = 0;
//reg[8:0]       addr_buffer;
//reg[31:0]      read_buffer = 0;
//assign icode = read_buffer[31:28];
//assign ifun  = read_buffer[27:24];
//assign rA    = read_buffer[23:20];
//assign rB    = read_buffer[19:16];
//assign valC  = read_buffer[15: 0];

wire[8:0]       addr_w;
wire[31:0]      read_w;
reg[8:0]        PC = 0;
reg             read = 0; //3
reg[3:0]        dstE_reg = 4'hF;
reg[3:0]        dstM = 0;
reg[31:0]       valM = 0;
reg[15:0]       valC;
reg             reg_rst;
wire[31:0]      aluA;
wire[31:0]      aluB;
reg[3:0]        alufun;
wire[31:0]      aluValE;
// Separate instruction fetching and decoding
// adding a pipeline
reg[3:0]        icode;
reg[3:0]        ifun;
reg[3:0]        rA;
reg[3:0]        rB;
//assign icode  = read_w[31:28];
//assign ifun   = read_w[27:24];
//assign rA     = read_w[23:20];
//assign rB     = read_w[19:16];
//
assign addr_w = (working) ? PC : addr;
assign aluA   = valA;
assign aluB   = valB;
assign valE   = aluValE;
//assign valE_reg = valE;
//assign valC   = read_w[15: 0];
//assign read   = (working) ? 1  : 0;

ram ram(
                .clock(clock),
                .addr(addr_w),
                .wr(wr),
                .wdata(wdata),
                .rd(read),
                .rdata(read_w)
);
regfile regfile(
                .dstE(dstE_reg),
                .valE(aluValE),
                .dstM(dstM),
                .valM(valM),
                .rA(rA),
                .rB(rB),
                .reset(reg_rst),
                .clock(clock),
                .r0(r0),
                .r1(r1),
                .r2(r2),
                .r3(r3),
                .r4(r4),
                .r5(r5),
                .r6(r6),
                .r7(r7),
                .valA(valA),
                .valB(valB)
);
alu alu(
        .aluA(aluA),
        .aluB(aluB),
        .alufun(alufun),
        .valE(aluValE)
);

initial begin
        reg_rst <= 1;
    #20 reg_rst <= 0;
end

always @(posedge clock) begin
    if(working)begin
        //addr_w <= PC;
        //read_buffer <= read_w;
        read = 1; 
        PC <= PC+1;
        icode <= read_w[31:28];
        ifun  <= read_w[27:24];
        valC  <= read_w[15: 0];//////////
        rA    <= read_w[23:20];
        rB    <= read_w[19:16];
        case(read_w[31:24])
            8'h10: begin
                dstM <= read_w[19:16];
                valM <= read_w[15: 0]; 
            end            
            8'h20: begin
                alufun <= 0;
                dstE_reg <= rA;
                //valE_reg <= valE;
            end
            8'h21: begin
                alufun <= 1;
                dstE_reg <= rA;
                //valE_reg <= valE;
            end
            8'h22: begin
                alufun <= 2;
                dstE_reg <= rA;
               //valE_reg <= valE;
            end
            8'h23: begin
                alufun <= 3;
                dstE_reg <= rA;
               //valE_reg <= valE;
            end
        endcase
    end
    else begin
        if (wr)begin
        read = 0; //
        //addr_w <= addr;
        //read_buffer <= read_w;
        //icode <= read_buffer[31:28];
        end
    end
end
endmodule

module pro_tb2;
reg             clock;
reg[8:0]        addr;
reg             wr;
reg[31:0]       wdata;
reg             working;
wire[3:0]       icode;
wire[3:0]       ifun;
wire[3:0]       rA;
wire[3:0]       rB;
wire[15:0]      valC;
//wire[15:0]      valD;/////////
wire[31:0]      valB, valA; 
wire[31:0]      r0, r1, r2, r3, r4, r5, r6, r7;
wire[31:0]      valE;
processor processor(
                clock,
                addr,
                wr,
                wdata,
                working,
                icode,
                ifun,
                rA,
                rB,
                valC,
                r0, r1, r2, r3, r4, r5, r6, r7,
                valA,
                valB,
                valE
);
initial begin
    clock <= 0; addr <= 0; wr <= 0; wdata <= 0; working <= 0;
    #20         addr <= 0; wr <= 1; wdata <= 32'h10F00080;
    #20         addr <= 1; wr <= 1; wdata <= 32'h10F10081;
    #20         addr <= 2; wr <= 1; wdata <= 32'h10F20082;
    #20         addr <= 3; wr <= 1; wdata <= 32'h10F30083;
    #20         addr <= 4; wr <= 1; wdata <= 32'h10F40084;
    #20         addr <= 5; wr <= 1; wdata <= 32'h10F50085;
    #20         addr <= 6; wr <= 1; wdata <= 32'h10F60086;
    #20         addr <= 7; wr <= 1; wdata <= 32'h10F70087;
    #20         addr <= 8; wr <= 1; wdata <= 32'h20010000;
    #20         addr <= 9; wr <= 1; wdata <= 32'h21230000;
    #20         addr <= 10;wr <= 1; wdata <= 32'h22450000;
    #20         addr <= 11;wr <= 1; wdata <= 32'h23670000;
    #20         addr <= 0; wr <= 0; wdata <= 0;
    #10         working <= 1;
    #500        $stop;
end
always #10 clock = ~clock;
initial begin
    $dumpfile("tb/pro_tb4.vcd");
    $dumpvars();
end
endmodule
*/
/*-----Testbench of processor (Task 1)-------//
module pro_tb;
reg             clock;
reg[8:0]        addr;
reg             wr;
reg[31:0]       wdata;
reg             working;
wire[3:0]       icode;
wire[3:0]       ifun;
wire[3:0]       rA;
wire[3:0]       rB;
wire[15:0]      valC; 
processor processor(
                clock,
                addr,
                wr,
                wdata,
                working,
                icode,
                ifun,
                rA,
                rB,
                valC
);
initial begin
    clock <= 0; addr <= 0; wdata <= 32'h00000000; wr <= 0; working <= 0;
    #20         addr <= 0; wdata <= 32'h10f00010; wr <= 1;
    #20         addr <= 1; wdata <= 32'h20010000;
    #20         addr <= 2; wdata <= 32'h21230000;
    #20         addr <= 3; wdata <= 32'h22450000;
    #20         addr <= 4; wdata <= 32'h23670000;
    #20         addr <= 0; wdata <= 32'h00000000; wr <= 0; working <= 1;
    //#20         working <= 1;
    #100        $stop;
end
always #10 clock = ~clock;
initial begin
    $dumpfile("tb/pro_tb.vcd");
    $dumpvars;
end
endmodule*/

tb/pro_tb.vcd
$date
	Tue May 31 01:42:43 2022
$end
$version
	Icarus Verilog
$end
$timescale
	10ps
$end
$scope module pro_tb $end
$var wire 16 ! valC [15:0] $end
$var wire 4 " rB [3:0] $end
$var wire 4 # rA [3:0] $end
$var wire 4 $ ifun [3:0] $end
$var wire 4 % icode [3:0] $end
$var reg 9 & addr [8:0] $end
$var reg 1 ' clock $end
$var reg 32 ( wdata [31:0] $end
$var reg 1 ) working $end
$var reg 1 * wr $end
$scope module processor $end
$var wire 32 + F_read [31:0] $end
$var wire 9 , addr [8:0] $end
$var wire 1 ' clock $end
$var wire 32 - wdata [31:0] $end
$var wire 1 ) working $end
$var wire 1 * wr $end
$var wire 16 . valC [15:0] $end
$var wire 32 / rdata [31:0] $end
$var wire 1 0 rd $end
$var wire 4 1 rB [3:0] $end
$var wire 4 2 rA [3:0] $end
$var wire 4 3 ifun [3:0] $end
$var wire 4 4 icode [3:0] $end
$var wire 9 5 addr_w [8:0] $end
$var reg 9 6 PC [8:0] $end
$scope module ram $end
$var wire 9 7 addr [8:0] $end
$var wire 1 ' clock $end
$var wire 1 0 rd $end
$var wire 32 8 wdata [31:0] $end
$var wire 1 * wr $end
$var reg 32 9 rdata [31:0] $end
$upscope $end
$upscope $end
$upscope $end
$enddefinitions $end
#0
$dumpvars
bz 9
b0 8
b0 7
b0 6
b0 5
bz 4
bz 3
bz 2
bz 1
00
bz /
bz .
b0 -
b0 ,
bz +
0*
0)
b0 (
0'
b0 &
bz %
bz $
bz #
bz "
bz !
$end
#1000
1'
#2000
1*
b10000111100000000000000010000 (
b10000111100000000000000010000 -
b10000111100000000000000010000 8
0'
#3000
1'
#4000
b1 5
b1 7
b100000000000010000000000000000 (
b100000000000010000000000000000 -
b100000000000010000000000000000 8
b1 &
b1 ,
0'
#5000
1'
#6000
b10 5
b10 7
b100001001000110000000000000000 (
b100001001000110000000000000000 -
b100001001000110000000000000000 8
b10 &
b10 ,
0'
#7000
1'
#8000
b11 5
b11 7
b100010010001010000000000000000 (
b100010010001010000000000000000 -
b100010010001010000000000000000 8
b11 &
b11 ,
0'
#9000
1'
#10000
b100 5
b100 7
b100011011001110000000000000000 (
b100011011001110000000000000000 -
b100011011001110000000000000000 8
b100 &
b100 ,
0'
#11000
1'
#12000
10
b0 5
b0 7
1)
0*
b0 (
b0 -
b0 8
b0 &
b0 ,
0'
#13000
b1 %
b1 4
b0 $
b0 3
b1111 #
b1111 2
b0 "
b0 1
b10000 !
b10000 .
b1 5
b1 7
b10000111100000000000000010000 +
b10000111100000000000000010000 /
b10000111100000000000000010000 9
b1 6
1'
#14000
0'
#15000
b10 5
b10 7
b10 %
b10 4
b0 #
b0 2
b1 "
b1 1
b0 !
b0 .
b10 6
b100000000000010000000000000000 +
b100000000000010000000000000000 /
b100000000000010000000000000000 9
1'
#16000
0'
#17000
b1 $
b1 3
b10 #
b10 2
b11 "
b11 1
b11 5
b11 7
b100001001000110000000000000000 +
b100001001000110000000000000000 /
b100001001000110000000000000000 9
b11 6
1'
#18000
0'
#19000
b100 5
b100 7
b10 $
b10 3
b100 #
b100 2
b101 "
b101 1
b100 6
b100010010001010000000000000000 +
b100010010001010000000000000000 /
b100010010001010000000000000000 9
1'
#20000
0'
#21000
b11 $
b11 3
b110 #
b110 2
b111 "
b111 1
b101 5
b101 7
b100011011001110000000000000000 +
b100011011001110000000000000000 /
b100011011001110000000000000000 9
b101 6
1'
#22000
0'
#23000
b110 5
b110 7
bx %
bx 4
bx $
bx 3
bx #
bx 2
bx "
bx 1
bx !
bx .
b110 6
bx +
bx /
bx 9
1'
#24000
0'
#25000
b111 5
b111 7
b111 6
1'
