ram.v
//存储器文件ram.v
`timescale 1ns/10ps
module ram(
input               clock,
input[8:0]          addr,
input               wr,
input[31:0]         wdata,
input               rd,
output reg[31:0]    rdata = 32'bz
);

reg[31:0]           ram[255:0];   //RAM variable
always @(posedge clock) begin
    if (wr)begin
        ram[addr] <= wdata;       //向RAM中写入数据
    end
    if (rd) begin
        rdata <= ram[addr];       //从RAM中读取数据
    end
    else begin
        rdata <= 32'bz;           //读写均无效时，为高阻态。
    end
end
endmodule

/*
//-----Testbench of ram-------//
module ram_tb;
reg             clock;
reg[8:0]        addr;
reg             wr, rd;
reg[31:0]       wdata;
wire[31:0]      rdata;

reg[63:0]       data_buffer;
reg[15:0]       addr_buffer;
ram ram(
                clock,
                addr,
                wr,
                wdata,
                rd,
                rdata
);
initial begin
    clock <= 0; rd <= 0; addr <= 0;
    data_buffer[63:32] = {4'h2, 4'h2, 4'h4, 4'h5, 8'h0, 8'h0}; 
    data_buffer[31:0]  = {4'h1, 4'h0, 4'hf, 4'h0, 4'h0, 4'h0, 4'h1, 4'h0};
    addr_buffer[15:0]  = {8'h0, 8'h1};
    addr <= addr_buffer[15:8]; wr <= 1; wdata <= data_buffer[63:32];

    #20  addr <= addr_buffer[7:0];  wr <= 1; wdata <= data_buffer[31:0];
    #20  addr <= addr_buffer[15:8]; wr <= 0; wdata <= 0; rd <= 1;
    #20  addr <= addr_buffer[7:0]; 
    #20  rd <= 0; addr <= addr_buffer[15:8];
    #50  $stop; 
end
always #10 clock = ~clock;
initial begin
    $dumpfile("tb/ram_tb.vcd");
    $dumpvars();
end
endmodule
*/

processor.v
//处理器Z的顶层文件processor.v
`timescale 1ns/10ps
module processor(
input           clock,
input[8:0]      addr,
input           wr,
input[31:0]     wdata,
input           working,
output[3:0]     icode,
output[3:0]     ifun,
output[3:0]     rA,
output[3:0]     rB,
output[15:0]    valC
);

reg[8:0]        PC = 0;
reg             read = 0; //3
//wire            read = 0;
wire[8:0]       addr_w;
wire[31:0]      read_w;
reg[8:0]        addr_buffer;
reg[31:0]       read_buffer = 0;

//assign icode = read_buffer[31:28];
//assign ifun  = read_buffer[27:24];
//assign rA    = read_buffer[23:20];
//assign rB    = read_buffer[19:16];
//assign valC  = read_buffer[15: 0];
assign icode  = read_w[31:28];
assign ifun   = read_w[27:24];
assign rA     = read_w[23:20];
assign rB     = read_w[19:16];
assign valC   = read_w[15: 0];
assign addr_w = (working) ? PC : addr;
//assign read   = (working) ? 1  : 0;
ram ram(
                .clock(clock),
                .addr(addr_w),
                .wr(wr),
                .wdata(wdata),
                .rd(read),
                .rdata(read_w)
);
always @(posedge clock) begin
    if(working)begin
        read = 1; //
        //addr_w <= PC;
        //read_buffer <= read_w;
        PC <= PC+1;
    end
    else begin
        if (wr)begin
        read = 0; //
        //addr_w <= addr;
        //read_buffer <= read_w;
        //icode <= read_buffer[31:28];
        end
    end
end
endmodule

//-----Testbench of processor-------//
module pro_tb;
reg             clock;
reg[8:0]        addr;
reg             wr;
reg[31:0]       wdata;
reg             working;
wire[3:0]       icode;
wire[3:0]       ifun;
wire[3:0]       rA;
wire[3:0]       rB;
wire[15:0]      valC; 
processor processor(
                clock,
                addr,
                wr,
                wdata,
                working,
                icode,
                ifun,
                rA,
                rB,
                valC
);
initial begin
    clock <= 0; addr <= 0; wdata <= 32'h00000000; wr <= 0; working <= 0;
    #20         addr <= 0; wdata <= 32'h10f00010; wr <= 1;
    #20         addr <= 1; wdata <= 32'h20010000;
    #20         addr <= 2; wdata <= 32'h21230000;
    #20         addr <= 3; wdata <= 32'h22450000;
    #20         addr <= 4; wdata <= 32'h23670000;
    #20         addr <= 0; wdata <= 32'h00000000; wr <= 0; working <= 1;
    //#20         working <= 1;
    #160        $stop;
end
always #10 clock = ~clock;
initial begin
    $dumpfile("tb/pro_tb.vcd");
    $dumpvars;
end
endmodule

tb/pro_tb.vcd
$date
	Sat May 28 22:00:56 2022
$end
$version
	Icarus Verilog
$end
$timescale
	10ps
$end
$scope module pro_tb $end
$var wire 16 ! valC [15:0] $end
$var wire 4 " rB [3:0] $end
$var wire 4 # rA [3:0] $end
$var wire 4 $ ifun [3:0] $end
$var wire 4 % icode [3:0] $end
$var reg 9 & addr [8:0] $end
$var reg 1 ' clock $end
$var reg 32 ( wdata [31:0] $end
$var reg 1 ) working $end
$var reg 1 * wr $end
$scope module processor $end
$var wire 9 + addr [8:0] $end
$var wire 1 ' clock $end
$var wire 32 , wdata [31:0] $end
$var wire 1 ) working $end
$var wire 1 * wr $end
$var wire 16 - valC [15:0] $end
$var wire 32 . read_w [31:0] $end
$var wire 4 / rB [3:0] $end
$var wire 4 0 rA [3:0] $end
$var wire 4 1 ifun [3:0] $end
$var wire 4 2 icode [3:0] $end
$var wire 9 3 addr_w [8:0] $end
$var reg 9 4 PC [8:0] $end
$var reg 1 5 read $end
$var reg 32 6 read_buffer [31:0] $end
$scope module ram $end
$var wire 9 7 addr [8:0] $end
$var wire 1 ' clock $end
$var wire 1 5 rd $end
$var wire 32 8 wdata [31:0] $end
$var wire 1 * wr $end
$var reg 32 9 rdata [31:0] $end
$upscope $end
$upscope $end
$upscope $end
$enddefinitions $end
#0
$dumpvars
bz 9
b0 8
b0 7
b0 6
05
b0 4
b0 3
bz 2
bz 1
bz 0
bz /
bz .
bz -
b0 ,
b0 +
0*
0)
b0 (
0'
b0 &
bz %
bz $
bz #
bz "
bz !
$end
#1000
1'
#2000
1*
b10000111100000000000000010000 (
b10000111100000000000000010000 ,
b10000111100000000000000010000 8
0'
#3000
1'
#4000
b1 3
b1 7
b100000000000010000000000000000 (
b100000000000010000000000000000 ,
b100000000000010000000000000000 8
b1 &
b1 +
0'
#5000
1'
#6000
b10 3
b10 7
b100001001000110000000000000000 (
b100001001000110000000000000000 ,
b100001001000110000000000000000 8
b10 &
b10 +
0'
#7000
1'
#8000
b11 3
b11 7
b100010010001010000000000000000 (
b100010010001010000000000000000 ,
b100010010001010000000000000000 8
b11 &
b11 +
0'
#9000
1'
#10000
b100 3
b100 7
b100011011001110000000000000000 (
b100011011001110000000000000000 ,
b100011011001110000000000000000 8
b100 &
b100 +
0'
#11000
1'
#12000
b0 3
b0 7
1)
0*
b0 (
b0 ,
b0 8
b0 &
b0 +
0'
#13000
b10000 !
b10000 -
b0 "
b0 /
b1111 #
b1111 0
b0 $
b0 1
b1 %
b1 2
b1 3
b1 7
b10000111100000000000000010000 .
b10000111100000000000000010000 9
b1 4
15
1'
#14000
0'
#15000
b10 3
b10 7
b0 !
b0 -
b1 "
b1 /
b0 #
b0 0
b10 %
b10 2
b10 4
b100000000000010000000000000000 .
b100000000000010000000000000000 9
1'
#16000
0'
#17000
b11 "
b11 /
b10 #
b10 0
b1 $
b1 1
b11 3
b11 7
b100001001000110000000000000000 .
b100001001000110000000000000000 9
b11 4
1'
#18000
0'
#19000
b100 3
b100 7
b101 "
b101 /
b100 #
b100 0
b10 $
b10 1
b100 4
b100010010001010000000000000000 .
b100010010001010000000000000000 9
1'
#20000
0'
#21000
b111 "
b111 /
b110 #
b110 0
b11 $
b11 1
b101 3
b101 7
b100011011001110000000000000000 .
b100011011001110000000000000000 9
b101 4
1'
#22000
0'
#23000
b110 3
b110 7
bx !
bx -
bx "
bx /
bx #
bx 0
bx $
bx 1
bx %
bx 2
b110 4
bx .
bx 9
1'
#24000
0'
#25000
b111 3
b111 7
b111 4
1'
#26000
0'
#27000
b1000 3
b1000 7
b1000 4
1'
